Workbook

Sheet Dashboard
A1: DINO DCF Dashboard
A2: Summary of the project
A3: Key Outputs
A4: Metric | B4: 2026E | C4: 2030E | D4: CAGR / Δ | F4: Metric | G4: Value | H4: Scenario
A5: Sales revenue (PLN '000) | B5: ='3-Statement Model'!H6 -> 38662461 | C5: ='3-Statement Model'!L6 -> 58834684 | D5: =POWER(C5/B5,1/4)-1 -> 0.1106724 | F5: Implied share price | G5: ='DCF Valuation'!B26 -> 10.657326 | H5: Scenario 1
A6: EBITDA (PLN '000) | B6: ='3-Statement Model'!H15 -> 2612845.3 | C6: ='3-Statement Model'!L15 -> 5158405.2 | D6: =POWER(C6/B6,1/4)-1 -> 0.18536047 | F6: Implied share price | G6: ='DCF Valuation'!B38 -> 40.884331 | H6: Scenario 2
A7: EBIT margin | B7: ='3-Statement Model'!H19 -> 0.052580935 | C7: ='3-Statement Model'!L19 -> 0.072676263 | D7: =C7-B7 -> 0.020095328 | F7: Current share price | G7: ='DCF Valuation'!B27 -> 32.84
A8: WACC | B8: ='Debt & WACC'!H38 -> 0.08451885 | C8: ='Debt & WACC'!L38 -> 0.08451885 | D8: =C8-B8 -> 0 | F8: Premium / (discount) | G8: ='DCF Valuation'!B28 -> -0.67547729 | H8: Scenario 1
A9: Net debt / (cash) | B9: ='3-Statement Model'!H89 -> -780096.71 | C9: ='3-Statement Model'!L89 -> -3922811.4 | D9: =C9-B9 -> -3142714.7 | F9: Premium / (discount) | G9: ='DCF Valuation'!B39 -> 0.24495527 | H9: Scenario 2
A11: Forecast Assumptions
A12: Metric | B12: 2026E | C12: 2027E | D12: 2028E | E12: 2029E | F12: 2030E
A13: LFL revenue growth | B13: =Assumptions!B26 -> 0.1495 | C13: =Assumptions!C26 -> 0.1336 | D13: =Assumptions!D26 -> 0.1178 | E13: =Assumptions!E26 -> 0.1021 | F13: =Assumptions!F26 -> 0.08968
A14: General inflation | B14: =Assumptions!B27 -> 0.04 | C14: =Assumptions!C27 -> 0.035 | D14: =Assumptions!D27 -> 0.03 | E14: =Assumptions!E27 -> 0.0275 | F14: =Assumptions!F27 -> 0.025
A15: Gross margin | B15: =Assumptions!B28 -> 0.237 | C15: =Assumptions!C28 -> 0.238 | D15: =Assumptions!D28 -> 0.239 | E15: =Assumptions!E28 -> 0.24 | F15: =Assumptions!F28 -> 0.24
A16: Capex % of sales | B16: =Assumptions!B32 -> 0.063 | C16: =Assumptions!C32 -> 0.061 | D16: =Assumptions!D32 -> 0.059 | E16: =Assumptions!E32 -> 0.057 | F16: =Assumptions!F32 -> 0.055
A17: Target equity weight | B17: =Assumptions!B16 -> 0.95 | C17: =Assumptions!B16 -> 0.95 | D17: =Assumptions!B16 -> 0.95 | E17: =Assumptions!B16 -> 0.95 | F17: =Assumptions!B16 -> 0.95
A18: Target debt weight | B18: =Assumptions!B17 -> 0.05 | C18: =Assumptions!B17 -> 0.05 | D18: =Assumptions!B17 -> 0.05 | E18: =Assumptions!B17 -> 0.05 | F18: =Assumptions!B17 -> 0.05
A19: Historical / Forecast Snapshot
A20: Year | B20: Sales revenue | C20: EBITDA | D20: EBIT margin | E20: UFCF | F20: WACC
A21: 2020 | B21: ='3-Statement Model'!B6 -> 10125815 | C21: ='3-Statement Model'!B15 -> 837859 | D21: ='3-Statement Model'!B19 -> 0.063176446 | F21: ='Debt & WACC'!B38 -> 0.032191038
A22: 2021 | B22: ='3-Statement Model'!C6 -> 13362012 | C22: ='3-Statement Model'!C15 -> 1023993 | D22: ='3-Statement Model'!C19 -> 0.058123732 | F22: ='Debt & WACC'!C38 -> 0.036203272
A23: 2022 | B23: ='3-Statement Model'!D6 -> 19801622 | C23: ='3-Statement Model'!D15 -> 1537819 | D23: ='3-Statement Model'!D19 -> 0.062504476 | F23: ='Debt & WACC'!D38 -> 0.079988477
A24: 2023 | B24: ='3-Statement Model'!E6 -> 25666255 | C24: ='3-Statement Model'!E15 -> 1875855 | D24: ='3-Statement Model'!E19 -> 0.059183819 | F24: ='Debt & WACC'!E38 -> 0.082561059
A25: 2024 | B25: ='3-Statement Model'!F6 -> 29273792 | C25: ='3-Statement Model'!F15 -> 1908330 | D25: ='3-Statement Model'!F19 -> 0.05121137 | F25: ='Debt & WACC'!F38 -> 0.080504583
A26: 2025 | B26: ='3-Statement Model'!G6 -> 33634155 | C26: ='3-Statement Model'!G15 -> 2041282 | D26: ='3-Statement Model'!G19 -> 0.045675326 | F26: ='Debt & WACC'!G38 -> 0.080380149
A27: 2026 | B27: ='3-Statement Model'!H6 -> 38662461 | C27: ='3-Statement Model'!H15 -> 2612845.3 | D27: ='3-Statement Model'!H19 -> 0.052580935 | E27: ='DCF Valuation'!B14 -> -1069990.6 | F27: ='Debt & WACC'!H38 -> 0.08451885
A28: 2027 | B28: ='3-Statement Model'!I6 -> 43827766 | C28: ='3-Statement Model'!I15 -> 3217465.5 | D28: ='3-Statement Model'!I19 -> 0.058411579 | E28: ='DCF Valuation'!C14 -> -240717.94 | F28: ='Debt & WACC'!I38 -> 0.08451885
A29: 2028 | B29: ='3-Statement Model'!J6 -> 48990677 | C29: ='3-Statement Model'!J15 -> 3867830.2 | D29: ='3-Statement Model'!J19 -> 0.063950332 | E29: ='DCF Valuation'!D14 -> 85687.823 | F29: ='Debt & WACC'!J38 -> 0.08451885
A30: 2029 | B30: ='3-Statement Model'!K6 -> 53992625 | C30: ='3-Statement Model'!K15 -> 4528471.9 | D30: ='3-Statement Model'!K19 -> 0.068872046 | E30: ='DCF Valuation'!E14 -> 457508.69 | F30: ='Debt & WACC'!K38 -> 0.08451885
A31: 2030 | B31: ='3-Statement Model'!L6 -> 58834684 | C31: ='3-Statement Model'!L15 -> 5158405.2 | D31: ='3-Statement Model'!L19 -> 0.072676263 | E31: ='DCF Valuation'!F14 -> 832829.51 | F31: ='Debt & WACC'!L38 -> 0.08451885

Sheet Assumptions
A1: Assumptions
A3: Static Valuation / Model Assumptions
A4: Metric | B4: Value | H4: Notes
A5: Risk-free rate | B5: 0.0588 | H5: 2026 Polish 10-year reference; forward WACC input, May 23, 2026 rate
A6: Beta | B6: 0.51 | H6: Equity beta input
A7: Equity risk premium | B7: 0.0533 | H7: Market ERP input
A8: Terminal growth rate | B8: 0.03
A9: Current share price (PLN) | B9: ='Source Data'!H100 -> 32.84
A10: Shares outstanding ('000) | B10: ='Source Data'!G97 -> 980400 | H10: Linked to 2025 share count; 2020-2024 were 1/10 of 2025
A11: Days in year | B11: 365 | H11: Used for working capital days
A12: Units divisor | B12: 1000 | H12: Used for unit conversions
A13: Minimum cash % of sales | B13: 0.02
A14: Interest income rate on average cash | B14: 0.02
A15: Statutory tax rate | B15: 0.19
A16: Target equity weight | B16: 0.95
A17: Target debt weight | B17: =1-B16 -> 0.05
A18: Historical Market Inputs
A19: Metric | B19: 2020A | C19: 2021A | D19: 2022A | E19: 2023A | F19: 2024A | G19: 2025A | H19: Source / notes
A20: DINO market price / share (PLN) | B20: ='Source Data'!B100 -> 200 | C20: ='Source Data'!C100 -> 300 | D20: ='Source Data'!D100 -> 330 | E20: ='Source Data'!E100 -> 420 | F20: ='Source Data'!F100 -> 400 | G20: ='Source Data'!G100 -> 43
A21: Risk-free rate | B21: ='Source Data'!B101 -> 0.015 | C21: ='Source Data'!C101 -> 0.0194 | D21: ='Source Data'!D101 -> 0.0605 | E21: ='Source Data'!E101 -> 0.0581 | F21: ='Source Data'!F101 -> 0.0553 | G21: ='Source Data'!G101 -> 0.055
A22: Shares outstanding ('000) | B22: ='Source Data'!B97 -> 98040 | C22: ='Source Data'!C97 -> 98040 | D22: ='Source Data'!D97 -> 98040 | E22: ='Source Data'!E97 -> 98040 | F22: ='Source Data'!F97 -> 98040 | G22: ='Source Data'!G97 -> 980400 | H22: 2020-2024 = 1/10 of 2025
A23: Market capitalization (PLN '000) | B23: =B20*B22 -> 19608000 | C23: =C20*C22 -> 29412000 | D23: =D20*D22 -> 32353200 | E23: =E20*E22 -> 41176800 | F23: =F20*F22 -> 39216000 | G23: =G20*G22 -> 42157200
A24: Operating Forecast Assumptions
A25: Metric | B25: 2026E | C25: 2027E | D25: 2028E | E25: 2029E | F25: 2030E | H25: Source / notes
A26: LFL revenue growth | B26: 0.1495 | C26: 0.1336 | D26: 0.1178 | E26: 0.1021 | F26: 0.08968 | H26: Primary revenue driver
A27: General inflation | B27: 0.04 | C27: 0.035 | D27: 0.03 | E27: 0.0275 | F27: 0.025
A28: Gross margin | B28: 0.237 | C28: 0.238 | D28: 0.239 | E28: 0.24 | F28: 0.24
A29: Store count growth | B29: 0.1 | C29: 0.09 | D29: 0.08 | E29: 0.07 | F29: 0.06
A30: Other operating income % of sales | B30: 0.0008 | C30: 0.0008 | D30: 0.0008 | E30: 0.0008 | F30: 0.0008 | H30: Support ratio
A31: D&A % of sales | B31: 0.015 | C31: 0.015 | D31: 0.015 | E31: 0.015 | F31: 0.015 | H31: Forecast D&A input
A32: Capex % of sales | B32: 0.063 | C32: 0.061 | D32: 0.059 | E32: 0.057 | F32: 0.055
A33: Inventory days | B33: 50 | C33: 50 | D33: 49.5 | E33: 49 | F33: 48.5
A34: Receivables days | B34: 4 | C34: 4 | D34: 4 | E34: 4 | F34: 4
A35: Payables days | B35: 74 | C35: 74 | D35: 73.5 | E35: 73 | F35: 72.5
A36: Fixed Asset Allocation Assumptions
A37: Metric | B37: 2026E | C37: 2027E | D37: 2028E | E37: 2029E | F37: 2030E
A38: PPE / ROU capex allocation | B38: 0.95 | C38: 0.95 | D38: 0.95 | E38: 0.95 | F38: 0.95
A39: Intangible capex allocation | B39: 0.05 | C39: 0.05 | D39: 0.05 | E39: 0.05 | F39: 0.05
A40: PPE / ROU D&A allocation | B40: 0.95 | C40: 0.95 | D40: 0.95 | E40: 0.95 | F40: 0.95
A41: Intangible D&A allocation | B41: 0.05 | C41: 0.05 | D41: 0.05 | E41: 0.05 | F41: 0.05
A42: Debt / Financing Assumptions
A43: Metric | B43: 2026E | C43: 2027E | D43: 2028E | E43: 2029E | F43: 2030E
A44: Bank loan net change | B44: -75000 | C44: -75000 | D44: -75000 | E44: -75000 | F44: -75000
A45: Bank loans current % of total | B45: 0.33 | C45: 0.33 | D45: 0.33 | E45: 0.33 | F45: 0.33
A46: Lease liability net change | B46: 15000 | C46: 15000 | D46: 15000 | E46: 15000 | F46: 15000
A47: Lease current % of total | B47: 0.21 | C47: 0.21 | D47: 0.21 | E47: 0.21 | F47: 0.21
A48: Bond net change | B48: -30000 | C48: -30000 | D48: -30000 | E48: -30000 | F48: -30000
A49: Bonds current % of total | B49: 0.25 | C49: 0.25 | D49: 0.25 | E49: 0.25 | F49: 0.25
A50: Pre-tax cost of interest-bearing debt | B50: 0.07 | C50: 0.07 | D50: 0.07 | E50: 0.07 | F50: 0.07
A51: Trade payables interest rate | B51: 0.011 | C51: 0.011 | D51: 0.011 | E51: 0.011 | F51: 0.011
A52: Other payables interest rate | B52: 0.0005 | C52: 0.0005 | D52: 0.0005 | E52: 0.0005 | F52: 0.0005
A53: Other financial expense / (income) | B53: 0 | C53: 0 | D53: 0 | E53: 0 | F53: 0
A54: Other financing / balancing item | B54: 0 | C54: 0 | D54: 0 | E54: 0 | F54: 0
A55: Dividends / distributions | B55: 0 | C55: 0 | D55: 0 | E55: 0 | F55: 0
A56: Other investing activities | B56: 0 | C56: 0 | D56: 0 | E56: 0 | F56: 0

Sheet Source Data
A1: Source Data
A3: Historical P&L
A4: Item | B4: 2020 | C4: 2021 | D4: 2022 | E4: 2023 | F4: 2024 | G4: 2025
A5: Sales revenue | B5: 10125815 | C5: 13362012 | D5: 19801622 | E5: 25666255 | F5: 29273792 | G5: 33634155
A6: Cost of sales | B6: -7521986 | C6: -10038342 | D6: -15038630 | E6: -19741459 | F6: -22463233 | G6: -25723078
A7: Gross profit on sales | B7: 2603829 | C7: 3323670 | D7: 4762992 | E7: 5924796 | F7: 6810559 | G7: 7911077
A8: Other operating income | B8: 7598 | C8: 14364 | D8: 16282 | E8: 13477 | F8: 24185 | G8: 29231
A9: Sales and marketing expenses | B9: -1668084 | C9: -2181963 | D9: -3080061 | E9: -3878421 | F9: -4678717 | G9: -5576262
A10: General administration expenses | B10: -99783 | C10: -117285 | D10: -143217 | E10: -173736 | F10: -233653 | G10: -302944
A11: Other operating expenses | B11: -5701 | C11: -14793 | D11: -18177 | E11: -10261 | F11: -14044 | G11: -19820
A12: Operating profit | B12: 837859 | C12: 1023993 | D12: 1537819 | E12: 1875855 | F12: 1908330 | G12: 2041282
A13: Financial income | B13: 3237 | C13: 1119 | D13: 5092 | E13: 10442 | F13: 6657 | G13: 8316
A14: Financial expenses | B14: -52096 | C14: -46703 | D14: -141293 | E14: -147316 | F14: -121424 | G14: -122945
A15: Profit before tax | B15: 789000 | C15: 978409 | D15: 1401618 | E15: 1738981 | F15: 1793563 | G15: 1926653
... A19: Profit attributable to non-controlling shareholders | B19: 0 | C19: 0 | D19: 0 | E19: 0 | F19: 749 | G19: 437
A20: Historical Balance Sheet
A21: Item | B21: 2020 | C21: 2021 | D21: 2022 | E21: 2023 | F21: 2024 | G21: 2025
A22: Property plant and equipment | B22: 3749480 | C22: 4911353 | D22: 6070032 | E22: 6874672 | F22: 8230915 | G22: 9774681
A23: Right-of-use assets | B23: 184538 | C23: 139931 | D23: 105116 | E23: 93499 | F23: 141350 | G23: 217006
A24: Intangible assets | B24: 99050 | C24: 96947 | D24: 94737 | E24: 115056 | F24: 169964 | G24: 176185
A25: Other non-financial assets (non-current) | B25: 6 | C25: 0 | D25: 0 | E25: 0 | F25: 0 | G25: 0
A26: Deferred tax assets | B26: 20738 | C26: 35116 | D26: 26468 | E26: 41323 | F26: 74149 | G26: 31376
A27: Total non-current assets | B27: 4053812 | C27: 5183347 | D27: 6296353 | E27: 7124550 | F27: 8616378 | G27: 10199248
A28: Inventories | B28: 875147 | C28: 1373463 | D28: 1978778 | E28: 2638859 | F28: 3081444 | G28: 3548100
A29: Trade and other receivables | B29: 86822 | C29: 144012 | D29: 274872 | E29: 330389 | F29: 376480 | G29: 372038
A30: Income tax receivables | B30: 2 | C30: 55 | D30: 0 | E30: 103 | F30: 220 | G30: 18596
A31: Other non-financial assets (current) | B31: 73367 | C31: 47712 | D31: 69096 | E31: 64049 | F31: 88186 | G31: 76477
A32: Other financial assets | B32: 942 | C32: 1327 | D32: 1242 | E32: 1376 | F32: 2064 | G32: 2007
... A61: TOTAL EQUITY AND LIABILITIES | B61: 5570510 | C61: 7168531 | D61: 9003059 | E61: 10377715 | F61: 13055794 | G61: 15171280
A62: Historical Cash Flow
A63: Item | B63: 2020 | C63: 2021 | D63: 2022 | E63: 2023 | F63: 2024 | G63: 2025
A64: Depreciation and amortization | B64: 198146 | C64: 247343 | D64: 300129 | E64: 356828 | F64: 409179 | G64: 505031
A65: (Profit)/loss on investment activity | B65: 2264 | C65: 7423 | D65: 14540 | E65: 6531 | F65: 10372 | G65: 16705
A66: Interest income | B66: -1131 | C66: -998 | D66: -4969 | E66: -9006 | F66: -6101 | G66: -7952
A67: Interest expense | B67: 52012 | C67: 46645 | D67: 141293 | E67: 147316 | F67: 121353 | G67: 122837
A68: Movement in trade receivables and other receivables | B68: -43201 | C68: -24880 | D68: -152796 | E68: -54245 | F68: -55966 | G68: 14973
A69: Movement in inventories | B69: -251152 | C69: -498316 | D69: -605315 | E69: -660081 | F69: -424123 | G69: -466656
A70: Movement in liabilities except for loans and borrowings | B70: 197916 | C70: 728449 | D70: 366502 | E70: 537055 | F70: 1126352 | G70: 948166
A71: Income tax paid | B71: -138680 | C71: -173004 | D71: -234653 | E71: -291839 | F71: -417176 | G71: -362312
A72: Net cash from operating activities | B72: 819922 | C72: 1326331 | D72: 1253422 | E72: 1771540 | F72: 2557453 | G72: 2697445
A73: Sale of property plant and equipment and intangible assets | B73: 1403 | C73: 4263 | D73: 6287 | E73: 5735 | F73: 2430 | G73: 3980
A74: Purchase of property plant and equipment and intangible assets | B74: -1002025 | C74: -1335604 | D74: -1445905 | E74: -1172863 | F74: -1561914 | G74: -2087043
... A89: Cash at the end of the period | B89: 480418 | C89: 418615 | D89: 382718 | E89: 218389 | F89: 891022 | G89: 954814
A90: Historical Operating Metrics
A91: Item | B91: 2020 | C91: 2021 | D91: 2022 | E91: 2023 | F91: 2024 | G91: 2025
A92: Store count (#) | B92: 1473 | C92: 1815 | D92: 2156 | E92: 2406 | F92: 2688 | G92: 3033
A93: Sales area ('000 sqm) | B93: 573 | C93: 710 | D93: 848 | E93: 948 | F93: 1061 | G93: 1200
A94: Average sales area / store (sqm) | B94: =B93*1000/B92 -> 389.00204 | C94: =C93*1000/C92 -> 391.18457 | D94: =D93*1000/D92 -> 393.32096 | E94: =E93*1000/E92 -> 394.01496 | F94: =F93*1000/F92 -> 394.71726 | G94: =G93*1000/G92 -> 395.64787
A95: Inflation / deflation (%) | B95: 0.034 | C95: 0.051 | D95: 0.144 | E95: 0.114 | F95: 0.036 | G95: 0.036
A96: Dino LfL (%) | B96: 0.126 | C96: 0.124 | D96: 0.285 | E96: 0.172 | F96: 0.053 | G96: 0.044
A97: Shares outstanding ('000) | B97: 98040 | C97: 98040 | D97: 98040 | E97: 98040 | F97: 98040 | G97: 980400
A98: Historical Market Data
A99: Item | B99: 2020 | C99: 2021 | D99: 2022 | E99: 2023 | F99: 2024 | G99: 2025 | H99: 2026
A100: DINO market price / share (PLN) | B100: 200 | C100: 300 | D100: 330 | E100: 420 | F100: 400 | G100: 43 | H100: 32.84
A101: Risk-free rate | B101: 0.015 | C101: 0.0194 | D101: 0.0605 | E101: 0.0581 | F101: 0.0553 | G101: 0.055 | H101: 0.0588

Sheet Operating Drivers
A1: Operating Drivers / Revenue Build
A2: Formula-driven operating bridge. Forecast revenue is driven by LFL growth; store metrics are operational KPIs.
A3: Metric | B3: 2020 | C3: 2021 | D3: 2022 | E3: 2023 | F3: 2024 | G3: 2025 | H3: 2026 | I3: 2027 | J3: 2028 | K3: 2029 | L3: 2030
A4: Period | B4: 2020A | C4: 2021A | D4: 2022A | E4: 2023A | F4: 2024A | G4: 2025A | H4: 2026E | I4: 2027E | J4: 2028E | K4: 2029E | L4: 2030E
A5: Store Roll-Forward & Revenue Build
A6: Store count (#) | B6: ='Source Data'!B92 -> 1473 | C6: ='Source Data'!C92 -> 1815 | D6: ='Source Data'!D92 -> 2156 | E6: ='Source Data'!E92 -> 2406 | F6: ='Source Data'!F92 -> 2688 | G6: ='Source Data'!G92 -> 3033 | H6: =G6*(1+Assumptions!B29) -> 3336.3 | I6: =H6*(1+Assumptions!C29) -> 3636.567 | J6: =I6*(1+Assumptions!D29) -> 3927.4924 | K6: =J6*(1+Assumptions!E29) -> 4202.4168 | L6: =K6*(1+Assumptions!F29) -> 4454.5618
A7: Store count growth | C7: =C6/B6-1 -> 0.23217923 | D7: =D6/C6-1 -> 0.18787879 | E7: =E6/D6-1 -> 0.11595547 | F7: =F6/E6-1 -> 0.11720698 | G7: =G6/F6-1 -> 0.12834821 | H7: =Assumptions!B29 -> 0.1 | I7: =Assumptions!C29 -> 0.09 | J7: =Assumptions!D29 -> 0.08 | K7: =Assumptions!E29 -> 0.07 | L7: =Assumptions!F29 -> 0.06
A8: Sales area ('000 sqm) | B8: ='Source Data'!B93 -> 573 | C8: ='Source Data'!C93 -> 710 | D8: ='Source Data'!D93 -> 848 | E8: ='Source Data'!E93 -> 948 | F8: ='Source Data'!F93 -> 1061 | G8: ='Source Data'!G93 -> 1200 | H8: =H6*H10/1000 -> 1320 | I8: =I6*I10/1000 -> 1438.8 | J8: =J6*J10/1000 -> 1553.904 | K8: =K6*K10/1000 -> 1662.6773 | L8: =L6*L10/1000 -> 1762.4379
A9: Sales area growth | C9: =C8/B8-1 -> 0.2390925 | D9: =D8/C8-1 -> 0.1943662 | E9: =E8/D8-1 -> 0.11792453 | F9: =F8/E8-1 -> 0.11919831 | G9: =G8/F8-1 -> 0.13100848 | H9: =H8/G8-1 -> 0.1 | I9: =I8/H8-1 -> 0.09 | J9: =J8/I8-1 -> 0.08 | ... L9: =L8/K8-1 -> 0.06
A10: Average sales area / store (sqm) | B10: ='Source Data'!B94 -> 389.00204 | C10: ='Source Data'!C94 -> 391.18457 | D10: ='Source Data'!D94 -> 393.32096 | E10: ='Source Data'!E94 -> 394.01496 | F10: ='Source Data'!F94 -> 394.71726 | G10: ='Source Data'!G94 -> 395.64787 | H10: =G10 -> 395.64787 | I10: =G10 -> 395.64787 | J10: =G10 -> 395.64787 | K10: =G10 -> 395.64787 | L10: =G10 -> 395.64787
A11: Revenue / store (PLN '000) | B11: =B13/B6 -> 6874.2804 | C11: =C13/C6 -> 7361.9901 | D11: =D13/D6 -> 9184.4258 | E11: =E13/E6 -> 10667.604 | F11: =F13/F6 -> 10890.548 | G11: =G13/G6 -> 11089.402 | H11: =H13/H6 -> 11588.425 | I11: =I13/I6 -> 12051.962 | ... L11: =L13/L6 -> 13207.738
A12: Revenue / store growth | C12: =C11/B11-1 -> 0.070947019 | D12: =D11/C11-1 -> 0.24754661 | E12: =E11/D11-1 -> 0.16148839 | F12: =F11/E11-1 -> 0.020899137 | G12: =G11/F11-1 -> 0.018259317 | H12: =H11/G11-1 -> 0.045 | I12: =I11/H11-1 -> 0.04 | J12: =J11/I11-1 -> 0.035 | ... L12: =L11/K11-1 -> 0.028
A13: Sales revenue (PLN '000) | B13: ='Source Data'!B5 -> 10125815 | C13: ='Source Data'!C5 -> 13362012 | D13: ='Source Data'!D5 -> 19801622 | E13: ='Source Data'!E5 -> 25666255 | F13: ='Source Data'!F5 -> 29273792 | G13: ='Source Data'!G5 -> 33634155 | H13: =G13*(1+Assumptions!B26) -> 38662461 | I13: =H13*(1+Assumptions!C26) -> 43827766 | J13: =I13*(1+Assumptions!D26) -> 48990677 | K13: =J13*(1+Assumptions!E26) -> 53992625 | L13: =K13*(1+Assumptions!F26) -> 58834684
A14: Revenue growth | C14: =C13/B13-1 -> 0.31959867 | D14: =D13/C13-1 -> 0.48193416 | E14: =E13/D13-1 -> 0.29616932 | F14: =F13/E13-1 -> 0.14055564 | G14: =G13/F13-1 -> 0.14895108 | H14: =Assumptions!B26 -> 0.1495 | I14: =Assumptions!C26 -> 0.1336 | J14: =Assumptions!D26 -> 0.1178 | K14: =Assumptions!E26 -> 0.1021 | L14: =Assumptions!F26 -> 0.08968
A15: Gross margin | B15: ='Source Data'!B7/B13 -> 0.2571476 | C15: ='Source Data'!C7/C13 -> 0.24874023 | D15: ='Source Data'!D7/D13 -> 0.24053545 | E15: ='Source Data'!E7/E13 -> 0.23083991 | F15: ='Source Data'!F7/F13 -> 0.23265039 | G15: ='Source Data'!G7/G13 -> 0.23520963 | H15: =Assumptions!B28 -> 0.237 | I15: =Assumptions!C28 -> 0.238 | J15: =Assumptions!D28 -> 0.239 | K15: =Assumptions!E28 -> 0.24 | L15: =Assumptions!F28 -> 0.24
A16: EBITDA margin | B16: ='3-Statement Model'!B15/'3-Statement Model'!B6 -> 0.082744846 | C16: ='3-Statement Model'!C15/'3-Statement Model'!C6 -> 0.076634642 | D16: ='3-Statement Model'!D15/'3-Statement Model'!D6 -> 0.077661264 | E16: ='3-Statement Model'!E15/'3-Statement Model'!E6 -> 0.073086432 | F16: ='3-Statement Model'!F15/'3-Statement Model'!F6 -> 0.065189026 | G16: ='3-Statement Model'!G15/'3-Statement Model'!G6 -> 0.060690747 | H16: ='3-Statement Model'!H15/'3-Statement Model'!H6 -> 0.067580935 | I16: ='3-Statement Model'!I15/'3-Statement Model'!I6 -> 0.073411579 | ... L16: ='3-Statement Model'!L15/'3-Statement Model'!L6 -> 0.087676263
A17: EBIT margin | B17: ='3-Statement Model'!B18/'3-Statement Model'!B6 -> 0.063176446 | C17: ='3-Statement Model'!C18/'3-Statement Model'!C6 -> 0.058123732 | D17: ='3-Statement Model'!D18/'3-Statement Model'!D6 -> 0.062504476 | E17: ='3-Statement Model'!E18/'3-Statement Model'!E6 -> 0.059183819 | F17: ='3-Statement Model'!F18/'3-Statement Model'!F6 -> 0.05121137 | G17: ='3-Statement Model'!G18/'3-Statement Model'!G6 -> 0.045675326 | H17: ='3-Statement Model'!H18/'3-Statement Model'!H6 -> 0.052580935 | I17: ='3-Statement Model'!I18/'3-Statement Model'!I6 -> 0.058411579 | ... L17: ='3-Statement Model'!L18/'3-Statement Model'!L6 -> 0.072676263
A18: Capex % of sales | B18: =-'3-Statement Model'!B35/'3-Statement Model'!B6 -> 0.098957467 | C18: =-'3-Statement Model'!C35/'3-Statement Model'!C6 -> 0.099955306 | D18: =-'3-Statement Model'!D35/'3-Statement Model'!D6 -> 0.073019523 | E18: =-'3-Statement Model'!E35/'3-Statement Model'!E6 -> 0.045696694 | F18: =-'3-Statement Model'!F35/'3-Statement Model'!F6 -> 0.05335537 | G18: =-'3-Statement Model'!G35/'3-Statement Model'!G6 -> 0.062051299 | H18: =-'3-Statement Model'!H35/'3-Statement Model'!H6 -> 0.063 | I18: =-'3-Statement Model'!I35/'3-Statement Model'!I6 -> 0.061 | ... L18: =-'3-Statement Model'!L35/'3-Statement Model'!L6 -> 0.055
A19: Operating NWC % of sales | B19: ='3-Statement Model'!B90/'3-Statement Model'!B6 -> -0.077461814 | C19: ='3-Statement Model'!C90/'3-Statement Model'!C6 -> -0.078089737 | D19: ='3-Statement Model'!D90/'3-Statement Model'!D6 -> -0.03419629 | E19: ='3-Statement Model'!E90/'3-Statement Model'!E6 -> -0.021295666 | F19: ='3-Statement Model'!F90/'3-Statement Model'!F6 -> -0.042723403 | G19: ='3-Statement Model'!G90/'3-Statement Model'!G6 -> -0.050346352 | H19: ='3-Statement Model'!H90/'3-Statement Model'!H6 -> -0.066064218 | I19: ='3-Statement Model'!I90/'3-Statement Model'!I6 -> -0.065083985 | ... L19: ='3-Statement Model'!L90/'3-Statement Model'!L6 -> -0.063109317

Sheet 3-Statement Model
A1: Integrated Three-Statement Model
A2: All non-input cells are formula-driven from Source Data and Assumptions. Hardcoded values are isolated on Source Data and Assumptions only.
A3: Metric | B3: 2020 | C3: 2021 | D3: 2022 | E3: 2023 | F3: 2024 | G3: 2025 | H3: 2026 | I3: 2027 | J3: 2028 | K3: 2029 | L3: 2030
A4: Period | B4: 2020A | C4: 2021A | D4: 2022A | E4: 2023A | F4: 2024A | G4: 2025A | H4: 2026E | I4: 2027E | J4: 2028E | K4: 2029E | L4: 2030E
A5: Income Statement
A6: Sales revenue | B6: ='Source Data'!B5 -> 10125815 | C6: ='Source Data'!C5 -> 13362012 | D6: ='Source Data'!D5 -> 19801622 | E6: ='Source Data'!E5 -> 25666255 | F6: ='Source Data'!F5 -> 29273792 | G6: ='Source Data'!G5 -> 33634155 | H6: ='Operating Drivers'!H13 -> 38662461 | I6: ='Operating Drivers'!I13 -> 43827766 | J6: ='Operating Drivers'!J13 -> 48990677 | K6: ='Operating Drivers'!K13 -> 53992625 | L6: ='Operating Drivers'!L13 -> 58834684
A7: Revenue growth | C7: =C6/B6-1 -> 0.31959867 | D7: =D6/C6-1 -> 0.48193416 | E7: =E6/D6-1 -> 0.29616932 | F7: =F6/E6-1 -> 0.14055564 | G7: =G6/F6-1 -> 0.14895108 | H7: =H6/G6-1 -> 0.1495 | I7: =I6/H6-1 -> 0.1336 | J7: =J6/I6-1 -> 0.1178 | ... L7: =L6/K6-1 -> 0.08968
A8: Cost of sales | B8: ='Source Data'!B6 -> -7521986 | C8: ='Source Data'!C6 -> -10038342 | D8: ='Source Data'!D6 -> -15038630 | E8: ='Source Data'!E6 -> -19741459 | F8: ='Source Data'!F6 -> -22463233 | G8: ='Source Data'!G6 -> -25723078 | H8: =-H6*(1-Assumptions!B28) -> -29499458 | I8: =-I6*(1-Assumptions!C28) -> -33396758 | J8: =-J6*(1-Assumptions!D28) -> -37281905 | K8: =-K6*(1-Assumptions!E28) -> -41034395 | L8: =-L6*(1-Assumptions!F28) -> -44714359
A9: Gross profit | B9: =B6+B8 -> 2603829 | C9: =C6+C8 -> 3323670 | D9: =D6+D8 -> 4762992 | E9: =E6+E8 -> 5924796 | F9: =F6+F8 -> 6810559 | G9: =G6+G8 -> 7911077 | H9: =H6+H8 -> 9163003.3 | I9: =I6+I8 -> 10431008 | ... L9: =L6+L8 -> 14120324
A10: Gross margin | B10: =B9/B6 -> 0.2571476 | C10: =C9/C6 -> 0.24874023 | D10: =D9/D6 -> 0.24053545 | E10: =E9/E6 -> 0.23083991 | F10: =F9/F6 -> 0.23265039 | G10: =G9/G6 -> 0.23520963 | H10: =H9/H6 -> 0.237 | I10: =I9/I6 -> 0.238 | ... L10: =L9/L6 -> 0.24
A11: Other operating income | B11: ='Source Data'!B8 -> 7598 | C11: ='Source Data'!C8 -> 14364 | D11: ='Source Data'!D8 -> 16282 | E11: ='Source Data'!E8 -> 13477 | F11: ='Source Data'!F8 -> 24185 | G11: ='Source Data'!G8 -> 29231 | H11: =H6*Assumptions!B30 -> 30929.969 | I11: =I6*Assumptions!C30 -> 35062.213 | J11: =J6*Assumptions!D30 -> 39192.541 | K11: =K6*Assumptions!E30 -> 43194.1 | L11: =L6*Assumptions!F30 -> 47067.747
A12: Sales & marketing expenses | B12: ='Source Data'!B9 -> -1668084 | C12: ='Source Data'!C9 -> -2181963 | D12: ='Source Data'!D9 -> -3080061 | E12: ='Source Data'!E9 -> -3878421 | F12: ='Source Data'!F9 -> -4678717 | G12: ='Source Data'!G9 -> -5576262 | H12: =G12*(1+Assumptions!B27+Assumptions!B29-2%) -> -6245413.4 | I12: =H12*(1+Assumptions!C27+Assumptions!C29-2%) -> -6901181.9 | J12: =I12*(1+Assumptions!D27+Assumptions!D29-2%) -> -7522288.2 | K12: =J12*(1+Assumptions!E27+Assumptions!E29-2%) -> -8105265.6 | L12: =K12*(1+Assumptions!F27+Assumptions!F29-2%) -> -8632107.8
A13: General & administration expenses | B13: ='Source Data'!B10 -> -99783 | C13: ='Source Data'!C10 -> -117285 | D13: ='Source Data'!D10 -> -143217 | E13: ='Source Data'!E10 -> -173736 | F13: ='Source Data'!F10 -> -233653 | G13: ='Source Data'!G10 -> -302944 | H13: =G13*(1+Assumptions!B27) -> -315061.76 | I13: =H13*(1+Assumptions!C27) -> -326088.92 | J13: =I13*(1+Assumptions!D27) -> -335871.59 | K13: =J13*(1+Assumptions!E27) -> -345108.06 | L13: =K13*(1+Assumptions!F27) -> -353735.76
A14: Other operating expenses | B14: ='Source Data'!B11 -> -5701 | C14: ='Source Data'!C11 -> -14793 | D14: ='Source Data'!D11 -> -18177 | E14: ='Source Data'!E11 -> -10261 | F14: ='Source Data'!F11 -> -14044 | G14: ='Source Data'!G11 -> -19820 | H14: =G14*(1+Assumptions!B27) -> -20612.8 | I14: =H14*(1+Assumptions!C27) -> -21334.248 | J14: =I14*(1+Assumptions!D27) -> -21974.275 | K14: =J14*(1+Assumptions!E27) -> -22578.568 | L14: =K14*(1+Assumptions!F27) -> -23143.032
A15: EBITDA | B15: =SUM(B6,B8,B11,B12,B13,B14) -> 837859 | C15: =SUM(C6,C8,C11,C12,C13,C14) -> 1023993 | D15: =SUM(D6,D8,D11,D12,D13,D14) -> 1537819 | E15: =SUM(E6,E8,E11,E12,E13,E14) -> 1875855 | F15: =SUM(F6,F8,F11,F12,F13,F14) -> 1908330 | G15: =SUM(G6,G8,G11,G12,G13,G14) -> 2041282 | H15: =SUM(H6,H8,H11,H12,H13,H14) -> 2612845.3 | I15: =SUM(I6,I8,I11,I12,I13,I14) -> 3217465.5 | ... L15: =SUM(L6,L8,L11,L12,L13,L14) -> 5158405.2
A16: EBITDA margin | B16: =B15/B6 -> 0.082744846 | C16: =C15/C6 -> 0.076634642 | D16: =D15/D6 -> 0.077661264 | E16: =E15/E6 -> 0.073086432 | F16: =F15/F6 -> 0.065189026 | G16: =G15/G6 -> 0.060690747 | H16: =H15/H6 -> 0.067580935 | I16: =I15/I6 -> 0.073411579 | ... L16: =L15/L6 -> 0.087676263
A17: D&A expense | B17: =-'Source Data'!B64 -> -198146 | C17: =-'Source Data'!C64 -> -247343 | D17: =-'Source Data'!D64 -> -300129 | E17: =-'Source Data'!E64 -> -356828 | F17: =-'Source Data'!F64 -> -409179 | G17: =-'Source Data'!G64 -> -505031 | H17: =-H6*Assumptions!B31 -> -579936.92 | I17: =-I6*Assumptions!C31 -> -657416.49 | J17: =-J6*Assumptions!D31 -> -734860.15 | K17: =-K6*Assumptions!E31 -> -809889.37 | L17: =-L6*Assumptions!F31 -> -882520.25
A18: EBIT | B18: =B15+B17 -> 639713 | C18: =C15+C17 -> 776650 | D18: =D15+D17 -> 1237690 | E18: =E15+E17 -> 1519027 | F18: =F15+F17 -> 1499151 | G18: =G15+G17 -> 1536251 | H18: =H15+H17 -> 2032908.3 | I18: =I15+I17 -> 2560049 | ... L18: =L15+L17 -> 4275884.9
A19: EBIT margin | B19: =B18/B6 -> 0.063176446 | C19: =C18/C6 -> 0.058123732 | D19: =D18/D6 -> 0.062504476 | E19: =E18/E6 -> 0.059183819 | F19: =F18/F6 -> 0.05121137 | G19: =G18/G6 -> 0.045675326 | H19: =H18/H6 -> 0.052580935 | I19: =I18/I6 -> 0.058411579 | ... L19: =L18/L6 -> 0.072676263
A20: Financial income | B20: ='Source Data'!B13 -> 3237 | C20: ='Source Data'!C13 -> 1119 | D20: ='Source Data'!D13 -> 5092 | E20: ='Source Data'!E13 -> 10442 | F20: ='Source Data'!F13 -> 6657 | G20: ='Source Data'!G13 -> 8316 | H20: =G44*Assumptions!B14 -> 19096.28 | I20: =H44*Assumptions!B14 -> 28908.574 | J20: =I44*Assumptions!B14 -> 32593.488 | K20: =J44*Assumptions!B14 -> 42707.569 | L20: =K44*Assumptions!B14 -> 59966.399
A21: Interest expense - debt / leases / bonds | B21: -30379 | C21: -26155 | D21: -124832 | E21: -127285 | F21: -90957 | G21: -67946 | H21: =-'Debt & WACC'!H20 -> -49723.24 | I21: =-'Debt & WACC'!I20 -> -43423.24 | J21: =-'Debt & WACC'!J20 -> -37123.24 | K21: =-'Debt & WACC'!K20 -> -30823.24 | L21: =-'Debt & WACC'!L20 -> -24523.24
A22: Interest expense - trade payables | B22: -18139 | C22: -20434 | D22: -15839 | E22: -19600 | F22: -29836 | G22: 54614 | H22: =-'Debt & WACC'!H18 -> -57139.929 | I22: =-'Debt & WACC'!I18 -> -86222.585 | J22: =-'Debt & WACC'!J18 -> -97741.922 | K22: =-'Debt & WACC'!K18 -> -108517.7 | L22: =-'Debt & WACC'!L18 -> -118783.77
A23: Interest expense - other payables | B23: -3494 | C23: -56 | D23: -622 | E23: -431 | F23: -560 | G23: -277 | H23: =-'Debt & WACC'!H19 -> 0 | I23: =-'Debt & WACC'!I19 -> 0 | J23: =-'Debt & WACC'!J19 -> 0 | K23: =-'Debt & WACC'!K19 -> 0 | L23: =-'Debt & WACC'!L19 -> 0
A24: Other financial expense / (income) | B24: -84 | C24: -58 | D24: 0 | E24: 0 | F24: -71 | G24: -108 | H24: =-Assumptions!B53 -> 0 | I24: =-Assumptions!C53 -> 0 | J24: =-Assumptions!D53 -> 0 | K24: =-Assumptions!E53 -> 0 | L24: =-Assumptions!F53 -> 0
A25: Total financial expenses | B25: =SUM(B21:B24) -> -52096 | C25: =SUM(C21:C24) -> -46703 | D25: =SUM(D21:D24) -> -141293 | E25: =SUM(E21:E24) -> -147316 | F25: =SUM(F21:F24) -> -121424 | G25: =SUM(G21:G24) -> -13717 | H25: =SUM(H21:H24) -> -106863.17 | I25: =SUM(I21:I24) -> -129645.82 | ... L25: =SUM(L21:L24) -> -143307.01
A26: Profit before tax | B26: =B18+B20+B25 -> 590854 | C26: =C18+C20+C25 -> 731066 | D26: =D18+D20+D25 -> 1101489 | E26: =E18+E20+E25 -> 1382153 | F26: =F18+F20+F25 -> 1384384 | G26: =G18+G20+G25 -> 1530850 | H26: =H18+H20+H25 -> 1945141.5 | I26: =I18+I20+I25 -> 2459311.8 | ... L26: =L18+L20+L25 -> 4192544.3
A27: Income tax | B27: ='Source Data'!B16 -> -145083 | C27: ='Source Data'!C16 -> -173106 | D27: ='Source Data'!D16 -> -269531 | E27: ='Source Data'!E16 -> -333654 | F27: ='Source Data'!F16 -> -287834 | G27: ='Source Data'!G16 -> -367856 | H27: =-H26*Assumptions!B15 -> -369576.88 | I27: =-I26*Assumptions!B15 -> -467269.23 | J27: =-J26*Assumptions!B15 -> -575832.69 | K27: =-K26*Assumptions!B15 -> -688170.34 | L27: =-L26*Assumptions!B15 -> -796583.42
A28: Net income | B28: =B26+B27 -> 445771 | C28: =C26+C27 -> 557960 | D28: =D26+D27 -> 831958 | E28: =E26+E27 -> 1048499 | F28: =F26+F27 -> 1096550 | G28: =G26+G27 -> 1162994 | H28: =H26+H27 -> 1575564.6 | I28: =I26+I27 -> 1992042.5 | ... L28: =L26+L27 -> 3395960.9
A29: Net margin | B29: =B28/B6 -> 0.044023222 | C29: =C28/C6 -> 0.041757184 | D29: =D28/D6 -> 0.042014639 | E29: =E28/E6 -> 0.040851266 | F29: =F28/F6 -> 0.03745842 | G29: =G28/G6 -> 0.034577768 | H29: =H28/H6 -> 0.040751792 | I29: =I28/I6 -> 0.04545161 | ... L29: =L28/L6 -> 0.05772039
A30: Cash Flow Statement
A31: Net income | B31: =B28 -> 445771 | C31: =C28 -> 557960 | D31: =D28 -> 831958 | E31: =E28 -> 1048499 | F31: =F28 -> 1096550 | G31: =G28 -> 1162994 | H31: =H28 -> 1575564.6 | I31: =I28 -> 1992042.5 | ... L31: =L28 -> 3395960.9
A32: D&A addback | B32: =-B17 -> 198146 | C32: =-C17 -> 247343 | D32: =-D17 -> 300129 | E32: =-E17 -> 356828 | F32: =-F17 -> 409179 | G32: =-G17 -> 505031 | H32: =-H17 -> 579936.92 | I32: =-I17 -> 657416.49 | ... L32: =-L17 -> 882520.25
A33: Change in NWC & other operating items | B33: ='Source Data'!B72-B31-B32 -> 176005 | C33: ='Source Data'!C72-C31-C32 -> 521028 | D33: ='Source Data'!D72-D31-D32 -> 121335 | E33: ='Source Data'!E72-E31-E32 -> 366213 | F33: ='Source Data'!F72-F31-F32 -> 1051724 | G33: ='Source Data'!G72-G31-G32 -> 1029420 | H33: =-(H90-G90) -> 860848.26 | I33: =-(I90-H90) -> 298280.4 | J33: =-(J90-I90) -> 296428.15 | K33: =-(K90-J90) -> 286852.91 | L33: =-(L90-K90) -> 277249.95
A34: Cash flow from operating activities | B34: =SUM(B31:B33) -> 819922 | C34: =SUM(C31:C33) -> 1326331 | D34: =SUM(D31:D33) -> 1253422 | E34: =SUM(E31:E33) -> 1771540 | F34: =SUM(F31:F33) -> 2557453 | G34: =SUM(G31:G33) -> 2697445 | H34: =SUM(H31:H33) -> 3016349.8 | I34: =SUM(I31:I33) -> 2947739.4 | ... L34: =SUM(L31:L33) -> 4555731.1
A35: Capital expenditures | B35: ='Source Data'!B74 -> -1002025 | C35: ='Source Data'!C74 -> -1335604 | D35: ='Source Data'!D74 -> -1445905 | E35: ='Source Data'!E74 -> -1172863 | F35: ='Source Data'!F74 -> -1561914 | G35: ='Source Data'!G74 -> -2087043 | H35: =-H6*Assumptions!B32 -> -2435735.1 | I35: =-I6*Assumptions!C32 -> -2673493.7 | J35: =-J6*Assumptions!D32 -> -2890449.9 | K35: =-K6*Assumptions!E32 -> -3077579.6 | L35: =-L6*Assumptions!F32 -> -3235907.6
A36: Other investing activities | B36: ='Source Data'!B79-B35 -> 1889 | C36: ='Source Data'!C79-C35 -> 4876 | D36: ='Source Data'!D79-D35 -> 11342 | E36: ='Source Data'!E79-E35 -> 14607 | F36: ='Source Data'!F79-F35 -> -34995 | G36: ='Source Data'!G79-G35 -> 11989 | H36: =Assumptions!B56 -> 0 | I36: =Assumptions!C56 -> 0 | J36: =Assumptions!D56 -> 0 | K36: =Assumptions!E56 -> 0 | L36: =Assumptions!F56 -> 0
A37: Cash flow from investing activities | B37: =SUM(B35:B36) -> -1000136 | C37: =SUM(C35:C36) -> -1330728 | D37: =SUM(D35:D36) -> -1434563 | E37: =SUM(E35:E36) -> -1158256 | F37: =SUM(F35:F36) -> -1596909 | G37: =SUM(G35:G36) -> -2075054 | H37: =SUM(H35:H36) -> -2435735.1 | I37: =SUM(I35:I36) -> -2673493.7 | ... L37: =SUM(L35:L36) -> -3235907.6
A38: Debt / lease / bond net change | B38: =SUM('Source Data'!B43,'Source Data'!B53,'Source Data'!B44,'Source Data'!B54,'Source Data'!B45,'Source Data'!B55) -> 1473710 | C38: =SUM('Source Data'!C43,'Source Data'!C53,'Source Data'!C44,'Source Data'!C54,'Source Data'!C45,'Source Data'!C55)-SUM('Source Data'!B43,'Source Data'!B53,'Source Data'!B44,'Source Data'!B54,'Source Data'!B45,'Source Data'!B55) -> 1457 | D38: =SUM('Source Data'!D43,'Source Data'!D53,'Source Data'!D44,'Source Data'!D54,'Source Data'!D45,'Source Data'!D55)-SUM('Source Data'!C43,'Source Data'!C53,'Source Data'!C44,'Source Data'!C54,'Source Data'!C45,'Source Data'!C55) -> 309365 | E38: =SUM('Source Data'!E43,'Source Data'!E53,'Source Data'!E44,'Source Data'!E54,'Source Data'!E45,'Source Data'!E55)-SUM('Source Data'!D43,'Source Data'!D53,'Source Data'!D44,'Source Data'!D54,'Source Data'!D45,'Source Data'!D55) -> -611354 | F38: =SUM('Source Data'!F43,'Source Data'!F53,'Source Data'!F44,'Source Data'!F54,'Source Data'!F45,'Source Data'!F55)-SUM('Source Data'!E43,'Source Data'!E53,'Source Data'!E44,'Source Data'!E54,'Source Data'!E45,'Source Data'!E55) -> -86362 | G38: =SUM('Source Data'!G43,'Source Data'!G53,'Source Data'!G44,'Source Data'!G54,'Source Data'!G45,'Source Data'!G55)-SUM('Source Data'!F43,'Source Data'!F53,'Source Data'!F44,'Source Data'!F54,'Source Data'!F45,'Source Data'!F55) -> -331484 | H38: =Assumptions!B44+Assumptions!B46+Assumptions!B48 -> -90000 | I38: =Assumptions!C44+Assumptions!C46+Assumptions!C48 -> -90000 | J38: =Assumptions!D44+Assumptions!D46+Assumptions!D48 -> -90000 | K38: =Assumptions!E44+Assumptions!E46+Assumptions!E48 -> -90000 | L38: =Assumptions!F44+Assumptions!F46+Assumptions!F48 -> -90000
A39: Dividends / distributions | B39: =0 -> 0 | C39: =0 -> 0 | D39: =0 -> 0 | E39: =0 -> 0 | F39: =0 -> 0 | G39: =0 -> 0 | H39: =Assumptions!B55 -> 0 | I39: =Assumptions!C55 -> 0 | J39: =Assumptions!D55 -> 0 | K39: =Assumptions!E55 -> 0 | L39: =Assumptions!F55 -> 0
A40: Other financing / balancing item | B40: ='Source Data'!B86-B38-B39 -> -1207798 | C40: ='Source Data'!C86-C38-C39 -> -58863 | D40: ='Source Data'!D86-D38-D39 -> -164121 | E40: ='Source Data'!E86-E38-E39 -> -166259 | F40: ='Source Data'!F86-F38-F39 -> -201549 | G40: ='Source Data'!G86-G38-G39 -> -227115 | H40: =Assumptions!B54 -> 0 | I40: =Assumptions!C54 -> 0 | J40: =Assumptions!D54 -> 0 | K40: =Assumptions!E54 -> 0 | L40: =Assumptions!F54 -> 0
A41: Cash flow from financing activities | B41: =SUM(B38:B40) -> 265912 | C41: =SUM(C38:C40) -> -57406 | D41: =SUM(D38:D40) -> 145244 | E41: =SUM(E38:E40) -> -777613 | F41: =SUM(F38:F40) -> -287911 | G41: =SUM(G38:G40) -> -558599 | H41: =SUM(H38:H40) -> -90000 | I41: =SUM(I38:I40) -> -90000 | ... L41: =SUM(L38:L40) -> -90000
A42: Net increase / (decrease) in cash | B42: =SUM(B34,B37,B41) -> 85698 | C42: =SUM(C34,C37,C41) -> -61803 | D42: =SUM(D34,D37,D41) -> -35897 | E42: =SUM(E34,E37,E41) -> -164329 | F42: =SUM(F34,F37,F41) -> 672633 | G42: =SUM(G34,G37,G41) -> 63792 | H42: =SUM(H34,H37,H41) -> 490614.71 | I42: =SUM(I34,I37,I41) -> 184245.69 | ... L42: =SUM(L34,L37,L41) -> 1229823.5
A43: Cash at beginning of period | B43: ='Source Data'!B88 -> 394720 | C43: ='Source Data'!C88 -> 480418 | D43: ='Source Data'!D88 -> 418615 | E43: ='Source Data'!E88 -> 382718 | F43: ='Source Data'!F88 -> 218389 | G43: ='Source Data'!G88 -> 891022 | H43: =G44 -> 954814 | I43: =H44 -> 1445428.7 | J43: =I44 -> 1629674.4 | K43: =J44 -> 2135378.5 | L43: =K44 -> 2998319.9
A44: Cash at end of period | B44: ='Source Data'!B89 -> 480418 | C44: ='Source Data'!C89 -> 418615 | D44: ='Source Data'!D89 -> 382718 | E44: ='Source Data'!E89 -> 218389 | F44: ='Source Data'!F89 -> 891022 | G44: ='Source Data'!G89 -> 954814 | H44: =H43+H42 -> 1445428.7 | I44: =I43+I42 -> 1629674.4 | J44: =J43+J42 -> 2135378.5 | K44: =K43+K42 -> 2998319.9 | L44: =L43+L42 -> 4228143.4
A45: Balance Sheet
A46: PPE & ROU assets | B46: ='Source Data'!B22+'Source Data'!B23 -> 3934018 | C46: ='Source Data'!C22+'Source Data'!C23 -> 5051284 | D46: ='Source Data'!D22+'Source Data'!D23 -> 6175148 | E46: ='Source Data'!E22+'Source Data'!E23 -> 6968171 | F46: ='Source Data'!F22+'Source Data'!F23 -> 8372265 | G46: ='Source Data'!G22+'Source Data'!G23 -> 9991687 | H46: =G46-(H35*Assumptions!B38)-(H32*Assumptions!B40) -> 11754695 | I46: =H46-(I35*Assumptions!C38)-(I32*Assumptions!C40) -> 13669969 | J46: =I46-(J35*Assumptions!D38)-(J32*Assumptions!D40) -> 15717779 | K46: =J46-(K35*Assumptions!E38)-(K32*Assumptions!E40) -> 17872085 | L46: =K46-(L35*Assumptions!F38)-(L32*Assumptions!F40) -> 20107803
A47: Intangible assets | B47: ='Source Data'!B24 -> 99050 | C47: ='Source Data'!C24 -> 96947 | D47: ='Source Data'!D24 -> 94737 | E47: ='Source Data'!E24 -> 115056 | F47: ='Source Data'!F24 -> 169964 | G47: ='Source Data'!G24 -> 176185 | H47: =G47-(H35*Assumptions!B39)-(H32*Assumptions!B41) -> 268974.91 | I47: =H47-(I35*Assumptions!C39)-(I32*Assumptions!C41) -> 369778.77 | J47: =I47-(J35*Assumptions!D39)-(J32*Assumptions!D41) -> 477558.26 | K47: =J47-(K35*Assumptions!E39)-(K32*Assumptions!E41) -> 590942.77 | L47: =K47-(L35*Assumptions!F39)-(L32*Assumptions!F41) -> 708612.14
A48: Other non-current assets | B48: ='Source Data'!B25 -> 6 | C48: ='Source Data'!C25 -> 0 | D48: ='Source Data'!D25 -> 0 | E48: ='Source Data'!E25 -> 0 | F48: ='Source Data'!F25 -> 0 | G48: ='Source Data'!G25 -> 0 | H48: =G48 -> 0 | I48: =H48 -> 0 | J48: =I48 -> 0 | K48: =J48 -> 0 | L48: =K48 -> 0
A49: Deferred tax assets | B49: ='Source Data'!B26 -> 20738 | C49: ='Source Data'!C26 -> 35116 | D49: ='Source Data'!D26 -> 26468 | E49: ='Source Data'!E26 -> 41323 | F49: ='Source Data'!F26 -> 74149 | G49: ='Source Data'!G26 -> 31376 | H49: =G49 -> 31376 | I49: =H49 -> 31376 | J49: =I49 -> 31376 | K49: =J49 -> 31376 | L49: =K49 -> 31376
A50: Total non-current assets | B50: =SUM(B46:B49) -> 4053812 | C50: =SUM(C46:C49) -> 5183347 | D50: =SUM(D46:D49) -> 6296353 | E50: =SUM(E46:E49) -> 7124550 | F50: =SUM(F46:F49) -> 8616378 | G50: =SUM(G46:G49) -> 10199248 | H50: =SUM(H46:H49) -> 12055046 | I50: =SUM(I46:I49) -> 14071123 | ... L50: =SUM(L46:L49) -> 20847791
A51: Inventories | B51: ='Source Data'!B28 -> 875147 | C51: ='Source Data'!C28 -> 1373463 | D51: ='Source Data'!D28 -> 1978778 | E51: ='Source Data'!E28 -> 2638859 | F51: ='Source Data'!F28 -> 3081444 | G51: ='Source Data'!G28 -> 3548100 | H51: =H6/Assumptions!B11*Assumptions!B33 -> 5296227.6 | I51: =I6/Assumptions!B11*Assumptions!C33 -> 6003803.6 | J51: =J6/Assumptions!B11*Assumptions!D33 -> 6643941.1 | K51: =K6/Assumptions!B11*Assumptions!E33 -> 7248325 | L51: =L6/Assumptions!B11*Assumptions!F33 -> 7817759.3
A52: Trade and other receivables | B52: ='Source Data'!B29 -> 86822 | C52: ='Source Data'!C29 -> 144012 | D52: ='Source Data'!D29 -> 274872 | E52: ='Source Data'!E29 -> 330389 | F52: ='Source Data'!F29 -> 376480 | G52: ='Source Data'!G29 -> 372038 | H52: =H6/Assumptions!B11*Assumptions!B34 -> 423698.2 | I52: =I6/Assumptions!B11*Assumptions!C34 -> 480304.28 | J52: =J6/Assumptions!B11*Assumptions!D34 -> 536884.13 | K52: =K6/Assumptions!B11*Assumptions!E34 -> 591700 | L52: =L6/Assumptions!B11*Assumptions!F34 -> 644763.66
A53: Income tax receivables | B53: ='Source Data'!B30 -> 2 | C53: ='Source Data'!C30 -> 55 | D53: ='Source Data'!D30 -> 0 | E53: ='Source Data'!E30 -> 103 | F53: ='Source Data'!F30 -> 220 | G53: ='Source Data'!G30 -> 18596 | H53: =G53*(1+Assumptions!B27) -> 19339.84 | I53: =H53*(1+Assumptions!C27) -> 20016.734 | J53: =I53*(1+Assumptions!D27) -> 20617.236 | K53: =J53*(1+Assumptions!E27) -> 21184.21 | L53: =K53*(1+Assumptions!F27) -> 21713.816
A54: Other current assets | B54: ='Source Data'!B31 -> 73367 | C54: ='Source Data'!C31 -> 47712 | D54: ='Source Data'!D31 -> 69096 | E54: ='Source Data'!E31 -> 64049 | F54: ='Source Data'!F31 -> 88186 | G54: ='Source Data'!G31 -> 76477 | H54: =G54*(1+Assumptions!B27) -> 79536.08 | I54: =H54*(1+Assumptions!C27) -> 82319.843 | J54: =I54*(1+Assumptions!D27) -> 84789.438 | K54: =J54*(1+Assumptions!E27) -> 87121.148 | L54: =K54*(1+Assumptions!F27) -> 89299.176
A55: Other financial assets | B55: ='Source Data'!B32 -> 942 | C55: ='Source Data'!C32 -> 1327 | D55: ='Source Data'!D32 -> 1242 | E55: ='Source Data'!E32 -> 1376 | F55: ='Source Data'!F32 -> 2064 | G55: ='Source Data'!G32 -> 2007 | H55: =G55*(1+Assumptions!B27) -> 2087.28 | I55: =H55*(1+Assumptions!C27) -> 2160.3348 | J55: =I55*(1+Assumptions!D27) -> 2225.1448 | K55: =J55*(1+Assumptions!E27) -> 2286.3363 | L55: =K55*(1+Assumptions!F27) -> 2343.4947
A56: Cash and cash equivalents | B56: =B44 -> 480418 | C56: =C44 -> 418615 | D56: =D44 -> 382718 | E56: =E44 -> 218389 | F56: =F44 -> 891022 | G56: =G44 -> 954814 | H56: =H44 -> 1445428.7 | I56: =I44 -> 1629674.4 | ... L56: =L44 -> 4228143.4
A57: Total current assets | B57: =SUM(B51:B56) -> 1516698 | C57: =SUM(C51:C56) -> 1985184 | D57: =SUM(D51:D56) -> 2706706 | E57: =SUM(E51:E56) -> 3253165 | F57: =SUM(F51:F56) -> 4439416 | G57: =SUM(G51:G56) -> 4972032 | H57: =SUM(H51:H56) -> 7266317.7 | I57: =SUM(I51:I56) -> 8218279.2 | ... L57: =SUM(L51:L56) -> 12804023
A58: Total assets | B58: =SUM(B50,B57) -> 5570510 | C58: =SUM(C50,C57) -> 7168531 | D58: =SUM(D50,D57) -> 9003059 | E58: =SUM(E50,E57) -> 10377715 | F58: =SUM(F50,F57) -> 13055794 | G58: =SUM(G50,G57) -> 15171280 | H58: =SUM(H50,H57) -> 19321364 | I58: =SUM(I50,I57) -> 22289403 | ... L58: =SUM(L50,L57) -> 33651814
A59: Equity
A60: Share capital | B60: ='Source Data'!B37 -> 9804 | C60: ='Source Data'!C37 -> 9804 | D60: ='Source Data'!D37 -> 9804 | E60: ='Source Data'!E37 -> 9804 | F60: ='Source Data'!F37 -> 9804 | G60: ='Source Data'!G37 -> 9804 | H60: =G60 -> 9804 | I60: =H60 -> 9804 | J60: =I60 -> 9804 | K60: =J60 -> 9804 | L60: =K60 -> 9804
A61: Supplementary capital | B61: ='Source Data'!B38 -> 2063322 | C61: ='Source Data'!C38 -> 2707720 | D61: ='Source Data'!D38 -> 3512022 | E61: ='Source Data'!E38 -> 4652148 | F61: ='Source Data'!F38 -> 6058912 | G61: ='Source Data'!G38 -> 7569927 | H61: =G61 -> 7569927 | I61: =H61 -> 7569927 | J61: =I61 -> 7569927 | K61: =J61 -> 7569927 | L61: =K61 -> 7569927
A62: Retained earnings | B62: ='Source Data'!B39 -> 185937 | C62: ='Source Data'!C39 -> 345166 | D62: ='Source Data'!D39 -> 674457 | E62: ='Source Data'!E39 -> 935859 | F62: ='Source Data'!F39 -> 1031871 | G62: ='Source Data'!G39 -> 1077742 | H62: =G62+H28+H39 -> 2653306.6 | I62: =H62+I28+I39 -> 4645349.1 | J62: =I62+J28+J39 -> 7100214.8 | K62: =J62+K28+K39 -> 10033994 | L62: =K62+L28+L39 -> 13429955
A63: Other equity | B63: ='Source Data'!B40 -> 7500 | C63: ='Source Data'!C40 -> 7500 | D63: ='Source Data'!D40 -> 7500 | E63: ='Source Data'!E40 -> 7500 | F63: ='Source Data'!F40 -> -15436 | G63: ='Source Data'!G40 -> -4080 | H63: =G63 -> -4080 | I63: =H63 -> -4080 | J63: =I63 -> -4080 | K63: =J63 -> -4080 | L63: =K63 -> -4080
A64: Non-controlling interests | B64: ='Source Data'!B41 -> 0 | C64: ='Source Data'!C41 -> 0 | D64: ='Source Data'!D41 -> 0 | E64: ='Source Data'!E41 -> 0 | F64: ='Source Data'!F41 -> 17283 | G64: ='Source Data'!G41 -> 17720 | H64: =G64 -> 17720 | I64: =H64 -> 17720 | J64: =I64 -> 17720 | K64: =J64 -> 17720 | L64: =K64 -> 17720
A65: Total equity | B65: =SUM(B60:B64) -> 2266563 | C65: =SUM(C60:C64) -> 3070190 | D65: =SUM(D60:D64) -> 4203783 | E65: =SUM(E60:E64) -> 5605311 | F65: =SUM(F60:F64) -> 7102434 | G65: =SUM(G60:G64) -> 8671113 | H65: =SUM(H60:H64) -> 10246678 | I65: =SUM(I60:I64) -> 12238720 | ... L65: =SUM(L60:L64) -> 21023326
A66: Liabilities
A67: Bank loans (non-current) | B67: ='Debt & WACC'!B6 -> 725851 | C67: ='Debt & WACC'!C6 -> 583014 | D67: ='Debt & WACC'!D6 -> 690862 | E67: ='Debt & WACC'!E6 -> 469629 | F67: ='Debt & WACC'!F6 -> 272219 | G67: ='Debt & WACC'!G6 -> 312861 | H67: ='Debt & WACC'!H6 -> 266517.29 | I67: ='Debt & WACC'!I6 -> 216267.29 | ... L67: ='Debt & WACC'!L6 -> 65517.29
A68: Lease liabilities (non-current) | B68: ='Debt & WACC'!B8 -> 67876 | C68: ='Debt & WACC'!C8 -> 46621 | D68: ='Debt & WACC'!D8 -> 34673 | E68: ='Debt & WACC'!E8 -> 35612 | F68: ='Debt & WACC'!F8 -> 60818 | G68: ='Debt & WACC'!G8 -> 87851 | H68: ='Debt & WACC'!H8 -> 99273.77 | I68: ='Debt & WACC'!I8 -> 111123.77 | ... L68: ='Debt & WACC'!L8 -> 146673.77
A69: Bonds (non-current) | B69: ='Debt & WACC'!B10 -> 419936 | C69: ='Debt & WACC'!C10 -> 450000 | D69: ='Debt & WACC'!D10 -> 370000 | E69: ='Debt & WACC'!E10 -> 370000 | F69: ='Debt & WACC'!F10 -> 170000 | G69: ='Debt & WACC'!G10 -> 0 | H69: ='Debt & WACC'!H10 -> 106411.5 | I69: ='Debt & WACC'!I10 -> 83911.5 | ... L69: ='Debt & WACC'!L10 -> 16411.5
A70: Other liabilities (non-current) | B70: ='Source Data'!B46+'Source Data'!B47 -> 180 | C70: ='Source Data'!C46+'Source Data'!C47 -> 150 | D70: ='Source Data'!D46+'Source Data'!D47 -> 120 | E70: ='Source Data'!E46+'Source Data'!E47 -> 90 | F70: ='Source Data'!F46+'Source Data'!F47 -> 22996 | G70: ='Source Data'!G46+'Source Data'!G47 -> 11610 | H70: =G70 -> 11610 | I70: =H70 -> 11610 | J70: =I70 -> 11610 | K70: =J70 -> 11610 | L70: =K70 -> 11610
A71: Employee benefits (non-current) | B71: ='Source Data'!B48 -> 2844 | C71: ='Source Data'!C48 -> 4827 | D71: ='Source Data'!D48 -> 5794 | E71: ='Source Data'!E48 -> 10900 | F71: ='Source Data'!F48 -> 14142 | G71: ='Source Data'!G48 -> 18041 | H71: =G71*(1+Assumptions!B27) -> 18762.64 | I71: =H71*(1+Assumptions!C27) -> 19419.332 | J71: =I71*(1+Assumptions!D27) -> 20001.912 | K71: =J71*(1+Assumptions!E27) -> 20551.965 | L71: =K71*(1+Assumptions!F27) -> 21065.764
A72: Deferred tax liability | B72: ='Source Data'!B49 -> 6555 | C72: ='Source Data'!C49 -> 8187 | D72: ='Source Data'!D49 -> 7700 | E72: ='Source Data'!E49 -> 6880 | F72: ='Source Data'!F49 -> 30336 | G72: ='Source Data'!G49 -> 4609 | H72: =G72 -> 4609 | I72: =H72 -> 4609 | J72: =I72 -> 4609 | K72: =J72 -> 4609 | L72: =K72 -> 4609
A73: Accruals & deferred revenue (non-current) | B73: ='Source Data'!B50 -> 14 | C73: ='Source Data'!C50 -> 5 | D73: ='Source Data'!D50 -> 0 | E73: ='Source Data'!E50 -> 0 | F73: ='Source Data'!F50 -> 0 | G73: ='Source Data'!G50 -> 0 | H73: =G73 -> 0 | I73: =H73 -> 0 | J73: =I73 -> 0 | K73: =J73 -> 0 | L73: =K73 -> 0
A74: Total non-current liabilities | B74: =SUM(B67:B73) -> 1223256 | C74: =SUM(C67:C73) -> 1092804 | D74: =SUM(D67:D73) -> 1109149 | E74: =SUM(E67:E73) -> 893111 | F74: =SUM(F67:F73) -> 570511 | G74: =SUM(G67:G73) -> 434972 | H74: =SUM(H67:H73) -> 507184.2 | I74: =SUM(I67:I73) -> 446940.89 | ... L74: =SUM(L67:L73) -> 265887.32
A75: Trade and other payables | B75: ='Source Data'!B52 -> 1695163 | C75: ='Source Data'!C52 -> 2454051 | D75: ='Source Data'!D52 -> 2651049 | E75: ='Source Data'!E52 -> 3095968 | F75: ='Source Data'!F52 -> 4362006 | G75: ='Source Data'!G52 -> 5194539 | H75: =H6/Assumptions!B11*Assumptions!B35 -> 7838416.8 | I75: =I6/Assumptions!B11*Assumptions!C35 -> 8885629.3 | J75: =J6/Assumptions!B11*Assumptions!D35 -> 9865245.9 | K75: =K6/Assumptions!B11*Assumptions!E35 -> 10798525 | L75: =L6/Assumptions!B11*Assumptions!F35 -> 11686341
A76: Bank loans (current) | B76: ='Debt & WACC'!B7 -> 216868 | C76: ='Debt & WACC'!C7 -> 196169 | D76: ='Debt & WACC'!D7 -> 410157 | E76: ='Debt & WACC'!E7 -> 278588 | F76: ='Debt & WACC'!F7 -> 361034 | G76: ='Debt & WACC'!G7 -> 159926 | H76: ='Debt & WACC'!H7 -> 131269.71 | I76: ='Debt & WACC'!I7 -> 106519.71 | ... L76: ='Debt & WACC'!L7 -> 32269.71
A77: Lease liabilities (current) | B77: ='Debt & WACC'!B9 -> 42249 | C77: ='Debt & WACC'!C9 -> 27721 | D77: ='Debt & WACC'!D9 -> 17893 | E77: ='Debt & WACC'!E9 -> 14565 | F77: ='Debt & WACC'!F9 -> 17900 | G77: ='Debt & WACC'!G9 -> 22812 | H77: ='Debt & WACC'!H9 -> 26389.23 | I77: ='Debt & WACC'!I9 -> 29539.23 | ... L77: ='Debt & WACC'!L9 -> 38989.23
A78: Bonds (current) | B78: ='Debt & WACC'!B11 -> 930 | C78: ='Debt & WACC'!C11 -> 171642 | D78: ='Debt & WACC'!D11 -> 260947 | E78: ='Debt & WACC'!E11 -> 4784 | F78: ='Debt & WACC'!F11 -> 204845 | G78: ='Debt & WACC'!G11 -> 171882 | H78: ='Debt & WACC'!H11 -> 35470.5 | I78: ='Debt & WACC'!I11 -> 27970.5 | ... L78: ='Debt & WACC'!L11 -> 5470.5
A79: Employee benefits (current) | B79: ='Source Data'!B56 -> 1332 | C79: ='Source Data'!C56 -> 1944 | D79: ='Source Data'!D56 -> 229660 | E79: ='Source Data'!E56 -> 307273 | F79: ='Source Data'!F56 -> 382575 | G79: ='Source Data'!G56 -> 464694 | H79: =G79*(1+Assumptions!B27) -> 483281.76 | I79: =H79*(1+Assumptions!C27) -> 500196.62 | J79: =I79*(1+Assumptions!D27) -> 515202.52 | K79: =J79*(1+Assumptions!E27) -> 529370.59 | L79: =K79*(1+Assumptions!F27) -> 542604.85
A80: Income tax liabilities | B80: ='Source Data'!B57 -> 80509 | C80: ='Source Data'!C57 -> 93017 | D80: ='Source Data'!D57 -> 120034 | E80: ='Source Data'!E57 -> 176736 | F80: ='Source Data'!F57 -> 50612 | G80: ='Source Data'!G57 -> 47605 | H80: =G80*(1+Assumptions!B27) -> 49509.2 | I80: =H80*(1+Assumptions!C27) -> 51242.022 | J80: =I80*(1+Assumptions!D27) -> 52779.283 | K80: =J80*(1+Assumptions!E27) -> 54230.713 | L80: =K80*(1+Assumptions!F27) -> 55586.481
A81: Deferred income (current) | B81: ='Source Data'!B58 -> 43640 | C81: ='Source Data'!C58 -> 60993 | D81: ='Source Data'!D58 -> 387 | E81: ='Source Data'!E58 -> 1379 | F81: ='Source Data'!F58 -> 3877 | G81: ='Source Data'!G58 -> 3737 | H81: =G81*(1+Assumptions!B27) -> 3886.48 | I81: =H81*(1+Assumptions!C27) -> 4022.5068 | J81: =I81*(1+Assumptions!D27) -> 4143.182 | K81: =J81*(1+Assumptions!E27) -> 4257.1195 | L81: =K81*(1+Assumptions!F27) -> 4363.5475
A82: Other current liabilities / (assets), net | B82: ='Source Data'!B59-SUM(B75:B81) -> 0 | C82: ='Source Data'!C59-SUM(C75:C81) -> 0 | D82: ='Source Data'!D59-SUM(D75:D81) -> 0 | E82: ='Source Data'!E59-SUM(E75:E81) -> 0 | F82: ='Source Data'!F59-SUM(F75:F81) -> 0 | G82: ='Source Data'!G59-SUM(G75:G81) -> 0 | H82: =H58-H65-H74-SUM(H75:H81) -> -721.64 | I82: =I58-I65-I74-SUM(I75:I81) -> -1378.3324 | J82: =J58-J65-J74-SUM(J75:J81) -> -1960.9124 | K82: =K58-K65-K74-SUM(K75:K81) -> -2510.965 | L82: =L58-L65-L74-SUM(L75:L81) -> -3024.7641
A83: Total current liabilities | B83: =SUM(B75:B82) -> 2080691 | C83: =SUM(C75:C82) -> 3005537 | D83: =SUM(D75:D82) -> 3690127 | E83: =SUM(E75:E82) -> 3879293 | F83: =SUM(F75:F82) -> 5382849 | G83: =SUM(G75:G82) -> 6065195 | H83: =SUM(H75:H82) -> 8567502 | I83: =SUM(I75:I82) -> 9603741.5 | ... L83: =SUM(L75:L82) -> 12362601
A84: Total liabilities | B84: =SUM(B74,B83) -> 3303947 | C84: =SUM(C74,C83) -> 4098341 | D84: =SUM(D74,D83) -> 4799276 | E84: =SUM(E74,E83) -> 4772404 | F84: =SUM(F74,F83) -> 5953360 | G84: =SUM(G74,G83) -> 6500167 | H84: =SUM(H74,H83) -> 9074686.2 | I84: =SUM(I74,I83) -> 10050682 | ... L84: =SUM(L74,L83) -> 12628488
A85: Total equity & liabilities | B85: =B65+B84 -> 5570510 | C85: =C65+C84 -> 7168531 | D85: =D65+D84 -> 9003059 | E85: =E65+E84 -> 10377715 | F85: =F65+F84 -> 13055794 | G85: =G65+G84 -> 15171280 | H85: =H65+H84 -> 19321364 | I85: =I65+I84 -> 22289403 | ... L85: =L65+L84 -> 33651814
A86: Balance check | B86: =B58-B85 -> 0 | C86: =C58-C85 -> 0 | D86: =D58-D85 -> 0 | E86: =E58-E85 -> 0 | F86: =F58-F85 -> 0 | G86: =G58-G85 -> 0 | H86: =H58-H85 -> 0 | I86: =I58-I85 -> 0 | ... L86: =L58-L85 -> 0
A87: Cash flow check | B87: =B44-B43-B42 -> 0 | C87: =C44-C43-C42 -> 0 | D87: =D44-D43-D42 -> 0 | E87: =E44-E43-E42 -> 0 | F87: =F44-F43-F42 -> 0 | G87: =G44-G43-G42 -> 0 | H87: =H44-H43-H42 -> 0 | I87: =I44-I43-I42 -> 0 | ... L87: =L44-L43-L42 -> 0
A88: Total interest-bearing debt | B88: =SUM(B67,B68,B69,B76,B77,B78) -> 1473710 | C88: =SUM(C67,C68,C69,C76,C77,C78) -> 1475167 | D88: =SUM(D67,D68,D69,D76,D77,D78) -> 1784532 | E88: =SUM(E67,E68,E69,E76,E77,E78) -> 1173178 | F88: =SUM(F67,F68,F69,F76,F77,F78) -> 1086816 | G88: =SUM(G67,G68,G69,G76,G77,G78) -> 755332 | H88: =SUM(H67,H68,H69,H76,H77,H78) -> 665332 | I88: =SUM(I67,I68,I69,I76,I77,I78) -> 575332 | ... L88: =SUM(L67,L68,L69,L76,L77,L78) -> 305332
A89: Net debt | B89: =B88-B56 -> 993292 | C89: =C88-C56 -> 1056552 | D89: =D88-D56 -> 1401814 | E89: =E88-E56 -> 954789 | F89: =F88-F56 -> 195794 | G89: =G88-G56 -> -199482 | H89: =H88-H56 -> -780096.71 | I89: =I88-I56 -> -1054342.4 | ... L89: =L88-L56 -> -3922811.4
A90: Operating net working capital | B90: =SUM(B51:B55)-B75-B79-B80-B81 -> -784364 | C90: =SUM(C51:C55)-C75-C79-C80-C81 -> -1043436 | D90: =SUM(D51:D55)-D75-D79-D80-D81 -> -677142 | E90: =SUM(E51:E55)-E75-E79-E80-E81 -> -546580 | F90: =SUM(F51:F55)-F75-F79-F80-F81 -> -1250676 | G90: =SUM(G51:G55)-G75-G79-G80-G81 -> -1693357 | H90: =SUM(H51:H55)-H75-H79-H80-H81 -> -2554205.3 | I90: =SUM(I51:I55)-I75-I79-I80-I81 -> -2852485.7 | ... L90: =SUM(L51:L55)-L75-L79-L80-L81 -> -3713016.7

Sheet Debt & WACC
A1: Debt Schedule & WACC
A2: Forecast WACC uses explicit target capital structure. Market capitalization is shown as a reference only and does not drive WACC weights.
A3: Metric | B3: 2020 | C3: 2021 | D3: 2022 | E3: 2023 | F3: 2024 | G3: 2025 | H3: 2026 | I3: 2027 | J3: 2028 | K3: 2029 | L3: 2030
A4: Period | B4: 2020A | C4: 2021A | D4: 2022A | E4: 2023A | F4: 2024A | G4: 2025A | H4: 2026E | I4: 2027E | J4: 2028E | K4: 2029E | L4: 2030E
A5: Debt Schedule
A6: Bank loans (non-current) | B6: ='Source Data'!B43 -> 725851 | C6: ='Source Data'!C43 -> 583014 | D6: ='Source Data'!D43 -> 690862 | E6: ='Source Data'!E43 -> 469629 | F6: ='Source Data'!F43 -> 272219 | G6: ='Source Data'!G43 -> 312861 | H6: =(G6+G7+Assumptions!B44)*(1-Assumptions!B45) -> 266517.29 | I6: =(H6+H7+Assumptions!C44)*(1-Assumptions!C45) -> 216267.29 | J6: =(I6+I7+Assumptions!D44)*(1-Assumptions!D45) -> 166017.29 | K6: =(J6+J7+Assumptions!E44)*(1-Assumptions!E45) -> 115767.29 | L6: =(K6+K7+Assumptions!F44)*(1-Assumptions!F45) -> 65517.29
A7: Bank loans (current) | B7: ='Source Data'!B53 -> 216868 | C7: ='Source Data'!C53 -> 196169 | D7: ='Source Data'!D53 -> 410157 | E7: ='Source Data'!E53 -> 278588 | F7: ='Source Data'!F53 -> 361034 | G7: ='Source Data'!G53 -> 159926 | H7: =(G6+G7+Assumptions!B44)*Assumptions!B45 -> 131269.71 | I7: =(H6+H7+Assumptions!C44)*Assumptions!C45 -> 106519.71 | J7: =(I6+I7+Assumptions!D44)*Assumptions!D45 -> 81769.71 | K7: =(J6+J7+Assumptions!E44)*Assumptions!E45 -> 57019.71 | L7: =(K6+K7+Assumptions!F44)*Assumptions!F45 -> 32269.71
A8: Lease liabilities (non-current) | B8: ='Source Data'!B44 -> 67876 | C8: ='Source Data'!C44 -> 46621 | D8: ='Source Data'!D44 -> 34673 | E8: ='Source Data'!E44 -> 35612 | F8: ='Source Data'!F44 -> 60818 | G8: ='Source Data'!G44 -> 87851 | H8: =(G8+G9+Assumptions!B46)*(1-Assumptions!B47) -> 99273.77 | I8: =(H8+H9+Assumptions!C46)*(1-Assumptions!C47) -> 111123.77 | J8: =(I8+I9+Assumptions!D46)*(1-Assumptions!D47) -> 122973.77 | K8: =(J8+J9+Assumptions!E46)*(1-Assumptions!E47) -> 134823.77 | L8: =(K8+K9+Assumptions!F46)*(1-Assumptions!F47) -> 146673.77
A9: Lease liabilities (current) | B9: ='Source Data'!B54 -> 42249 | C9: ='Source Data'!C54 -> 27721 | D9: ='Source Data'!D54 -> 17893 | E9: ='Source Data'!E54 -> 14565 | F9: ='Source Data'!F54 -> 17900 | G9: ='Source Data'!G54 -> 22812 | H9: =(G8+G9+Assumptions!B46)*Assumptions!B47 -> 26389.23 | I9: =(H8+H9+Assumptions!C46)*Assumptions!C47 -> 29539.23 | J9: =(I8+I9+Assumptions!D46)*Assumptions!D47 -> 32689.23 | K9: =(J8+J9+Assumptions!E46)*Assumptions!E47 -> 35839.23 | L9: =(K8+K9+Assumptions!F46)*Assumptions!F47 -> 38989.23
A10: Bonds (non-current) | B10: ='Source Data'!B45 -> 419936 | C10: ='Source Data'!C45 -> 450000 | D10: ='Source Data'!D45 -> 370000 | E10: ='Source Data'!E45 -> 370000 | F10: ='Source Data'!F45 -> 170000 | G10: ='Source Data'!G45 -> 0 | H10: =(G10+G11+Assumptions!B48)*(1-Assumptions!B49) -> 106411.5 | I10: =(H10+H11+Assumptions!C48)*(1-Assumptions!C49) -> 83911.5 | J10: =(I10+I11+Assumptions!D48)*(1-Assumptions!D49) -> 61411.5 | K10: =(J10+J11+Assumptions!E48)*(1-Assumptions!E49) -> 38911.5 | L10: =(K10+K11+Assumptions!F48)*(1-Assumptions!F49) -> 16411.5
A11: Bonds (current) | B11: ='Source Data'!B55 -> 930 | C11: ='Source Data'!C55 -> 171642 | D11: ='Source Data'!D55 -> 260947 | E11: ='Source Data'!E55 -> 4784 | F11: ='Source Data'!F55 -> 204845 | G11: ='Source Data'!G55 -> 171882 | H11: =(G10+G11+Assumptions!B48)*Assumptions!B49 -> 35470.5 | I11: =(H10+H11+Assumptions!C48)*Assumptions!C49 -> 27970.5 | J11: =(I10+I11+Assumptions!D48)*Assumptions!D49 -> 20470.5 | K11: =(J10+J11+Assumptions!E48)*Assumptions!E49 -> 12970.5 | L11: =(K10+K11+Assumptions!F48)*Assumptions!F49 -> 5470.5
A12: Total interest-bearing debt | B12: =SUM(B6:B11) -> 1473710 | C12: =SUM(C6:C11) -> 1475167 | D12: =SUM(D6:D11) -> 1784532 | E12: =SUM(E6:E11) -> 1173178 | F12: =SUM(F6:F11) -> 1086816 | G12: =SUM(G6:G11) -> 755332 | H12: =SUM(H6:H11) -> 665332 | I12: =SUM(I6:I11) -> 575332 | ... L12: =SUM(L6:L11) -> 305332
A13: Cash and cash equivalents | B13: ='3-Statement Model'!B56 -> 480418 | C13: ='3-Statement Model'!C56 -> 418615 | D13: ='3-Statement Model'!D56 -> 382718 | E13: ='3-Statement Model'!E56 -> 218389 | F13: ='3-Statement Model'!F56 -> 891022 | G13: ='3-Statement Model'!G56 -> 954814 | H13: ='3-Statement Model'!H56 -> 1445428.7 | I13: ='3-Statement Model'!I56 -> 1629674.4 | ... L13: ='3-Statement Model'!L56 -> 4228143.4
A14: Net debt | B14: =B12-B13 -> 993292 | C14: =C12-C13 -> 1056552 | D14: =D12-D13 -> 1401814 | E14: =E12-E13 -> 954789 | F14: =F12-F13 -> 195794 | G14: =G12-G13 -> -199482 | H14: =H12-H13 -> -780096.71 | I14: =I12-I13 -> -1054342.4 | ... L14: =L12-L13 -> -3922811.4
A15: Average total debt | B15: =B12 -> 1473710 | C15: =AVERAGE(B12,C12) -> 1474438.5 | D15: =AVERAGE(C12,D12) -> 1629849.5 | E15: =AVERAGE(D12,E12) -> 1478855 | F15: =AVERAGE(E12,F12) -> 1129997 | G15: =AVERAGE(F12,G12) -> 921074 | H15: =AVERAGE(G12,H12) -> 710332 | I15: =AVERAGE(H12,I12) -> 620332 | J15: =AVERAGE(I12,J12) -> 530332 | ... L15: =AVERAGE(K12,L12) -> 350332
A16: Payables Interest Split
A17: Total financial interest expense | B17: =-'Source Data'!B14 -> 52096 | C17: =-'Source Data'!C14 -> 46703 | D17: =-'Source Data'!D14 -> 141293 | E17: =-'Source Data'!E14 -> 147316 | F17: =-'Source Data'!F14 -> 121424 | G17: =-'Source Data'!G14 -> 122945 | H17: =H20+H18+H19 -> 106863.17 | I17: =I20+I18+I19 -> 129645.82 | J17: =J20+J18+J19 -> 134865.16 | K17: =K20+K18+K19 -> 139340.94 | L17: =L20+L18+L19 -> 143307.01
A18: Interest expense - trade payables | B18: 18139 | C18: 20434 | D18: 15839 | E18: 19600 | F18: 29836 | G18: 54614 | H18: ='3-Statement Model'!G75*Assumptions!B51 -> 57139.929 | I18: ='3-Statement Model'!H75*Assumptions!C51 -> 86222.585 | J18: ='3-Statement Model'!I75*Assumptions!D51 -> 97741.922 | K18: ='3-Statement Model'!J75*Assumptions!E51 -> 108517.7 | L18: ='3-Statement Model'!K75*Assumptions!F51 -> 118783.77
A19: Interest expense - other | B19: =-SUM('3-Statement Model'!B23,'3-Statement Model'!B24) -> 3578 | C19: =-SUM('3-Statement Model'!C23,'3-Statement Model'!C24) -> 114 | D19: =-SUM('3-Statement Model'!D23,'3-Statement Model'!D24) -> 622 | E19: =-SUM('3-Statement Model'!E23,'3-Statement Model'!E24) -> 431 | F19: =-SUM('3-Statement Model'!F23,'3-Statement Model'!F24) -> 631 | G19: =-SUM('3-Statement Model'!G23,'3-Statement Model'!G24) -> 385 | H19: 0 | I19: 0 | J19: 0 | K19: 0 | L19: 0
A20: Interest expense - debt / leases / bonds | B20: =B17-B18-B19 -> 30379 | C20: =C17-C18-C19 -> 26155 | D20: =D17-D18-D19 -> 124832 | E20: =E17-E18-E19 -> 127285 | F20: =F17-F18-F19 -> 90957 | G20: =G17-G18-G19 -> 67946 | H20: =H15*Assumptions!B50 -> 49723.24 | I20: =I15*Assumptions!C50 -> 43423.24 | J20: =J15*Assumptions!D50 -> 37123.24 | K20: =K15*Assumptions!E50 -> 30823.24 | L20: =L15*Assumptions!F50 -> 24523.24
A21: Pre-tax cost of debt | B21: =B20/B15 -> 0.020613961 | C21: =C20/C15 -> 0.017738956 | D21: =D20/D15 -> 0.076591121 | E21: =E20/E15 -> 0.086069966 | F21: =F20/F15 -> 0.080493134 | G21: =G20/G15 -> 0.073768231 | H21: =H20/H15 -> 0.07 | I21: =I20/I15 -> 0.07 | ... L21: =L20/L15 -> 0.07
A22: WACC Calculation
A23: Reference market price / share (PLN) | B23: =Assumptions!B20 -> 200 | C23: =Assumptions!C20 -> 300 | D23: =Assumptions!D20 -> 330 | E23: =Assumptions!E20 -> 420 | F23: =Assumptions!F20 -> 400 | G23: =Assumptions!G20 -> 43 | H23: ='Source Data'!H100 -> 32.84 | I23: =H23*(1+Assumptions!C28) -> 40.65592 | J23: =I23*(1+Assumptions!D28) -> 50.372685 | K23: =J23*(1+Assumptions!E28) -> 62.462129 | L23: =K23*(1+Assumptions!F28) -> 77.45304
A24: Shares outstanding ('000) | B24: =Assumptions!B22 -> 98040 | C24: =Assumptions!C22 -> 98040 | D24: =Assumptions!D22 -> 98040 | E24: =Assumptions!E22 -> 98040 | F24: =Assumptions!F22 -> 98040 | G24: =Assumptions!G22 -> 980400 | H24: =Assumptions!B10 -> 980400 | I24: =Assumptions!B10 -> 980400 | J24: =Assumptions!B10 -> 980400 | K24: =Assumptions!B10 -> 980400 | L24: =Assumptions!B10 -> 980400
A25: Reference market capitalization | B25: =B23*B24 -> 19608000 | C25: =C23*C24 -> 29412000 | D25: =D23*D24 -> 32353200 | E25: =E23*E24 -> 41176800 | F25: =F23*F24 -> 39216000 | G25: =G23*G24 -> 42157200 | H25: =H23*H24 -> 32196336 | I25: =I23*I24 -> 39859064 | ... L25: =L23*L24 -> 75934961
A26: Total interest-bearing debt | B26: =B12 -> 1473710 | C26: =C12 -> 1475167 | D26: =D12 -> 1784532 | E26: =E12 -> 1173178 | F26: =F12 -> 1086816 | G26: =G12 -> 755332 | H26: =H12 -> 665332 | I26: =I12 -> 575332 | ... L26: =L12 -> 305332
A27: Cash and cash equivalents | B27: =B13 -> 480418 | C27: =C13 -> 418615 | D27: =D13 -> 382718 | E27: =E13 -> 218389 | F27: =F13 -> 891022 | G27: =G13 -> 954814 | H27: =H13 -> 1445428.7 | I27: =I13 -> 1629674.4 | ... L27: =L13 -> 4228143.4
A28: Net debt | B28: =B14 -> 993292 | C28: =C14 -> 1056552 | D28: =D14 -> 1401814 | E28: =E14 -> 954789 | F28: =F14 -> 195794 | G28: =G14 -> -199482 | H28: =H14 -> -780096.71 | I28: =I14 -> -1054342.4 | ... L28: =L14 -> -3922811.4
A29: Enterprise value | B29: =B25+B28 -> 20601292 | C29: =C25+C28 -> 30468552 | D29: =D25+D28 -> 33755014 | E29: =E25+E28 -> 42131589 | F29: =F25+F28 -> 39411794 | G29: =G25+G28 -> 41957718 | H29: =H25+H28 -> 31416239 | I29: =I25+I28 -> 38804722 | ... L29: =L25+L28 -> 72012149
A30: Tax rate | B30: =-'Source Data'!B16/'Source Data'!B15 -> 0.18388213 | C30: =-'Source Data'!C16/'Source Data'!C15 -> 0.17692601 | D30: =-'Source Data'!D16/'Source Data'!D15 -> 0.1922999 | E30: =-'Source Data'!E16/'Source Data'!E15 -> 0.19186754 | F30: =-'Source Data'!F16/'Source Data'!F15 -> 0.16048168 | G30: =-'Source Data'!G16/'Source Data'!G15 -> 0.19093007 | H30: =Assumptions!B15 -> 0.19 | I30: =Assumptions!B15 -> 0.19 | J30: =Assumptions!B15 -> 0.19 | K30: =Assumptions!B15 -> 0.19 | L30: =Assumptions!B15 -> 0.19
A31: After-tax cost of debt | B31: =B21*(1-B30) -> 0.016823422 | C31: =C21*(1-C30) -> 0.014600473 | D31: =D21*(1-D30) -> 0.061862656 | E31: =E21*(1-E30) -> 0.069555934 | F31: =F21*(1-F30) -> 0.067575461 | G31: =G21*(1-G30) -> 0.059683658 | H31: =H21*(1-H30) -> 0.0567 | I31: =I21*(1-I30) -> 0.0567 | ... L31: =L21*(1-L30) -> 0.0567
A32: Risk-free rate | B32: =Assumptions!B21 -> 0.015 | C32: =Assumptions!C21 -> 0.0194 | D32: =Assumptions!D21 -> 0.0605 | E32: =Assumptions!E21 -> 0.0581 | F32: =Assumptions!F21 -> 0.0553 | G32: =Assumptions!G21 -> 0.055 | H32: =Assumptions!B5 -> 0.0588 | I32: =Assumptions!B5 -> 0.0588 | J32: =Assumptions!B5 -> 0.0588 | K32: =Assumptions!B5 -> 0.0588 | L32: =Assumptions!B5 -> 0.0588
A33: Beta | B33: =Assumptions!B6 -> 0.51 | C33: =Assumptions!B6 -> 0.51 | D33: =Assumptions!B6 -> 0.51 | E33: =Assumptions!B6 -> 0.51 | F33: =Assumptions!B6 -> 0.51 | G33: =Assumptions!B6 -> 0.51 | H33: =Assumptions!B6 -> 0.51 | I33: =Assumptions!B6 -> 0.51 | J33: =Assumptions!B6 -> 0.51 | K33: =Assumptions!B6 -> 0.51 | L33: =Assumptions!B6 -> 0.51
A34: Equity risk premium | B34: =Assumptions!B7 -> 0.0533 | C34: =Assumptions!B7 -> 0.0533 | D34: =Assumptions!B7 -> 0.0533 | E34: =Assumptions!B7 -> 0.0533 | F34: =Assumptions!B7 -> 0.0533 | G34: =Assumptions!B7 -> 0.0533 | H34: =Assumptions!B7 -> 0.0533 | I34: =Assumptions!B7 -> 0.0533 | J34: =Assumptions!B7 -> 0.0533 | K34: =Assumptions!B7 -> 0.0533 | L34: =Assumptions!B7 -> 0.0533
A35: Cost of equity | B35: =B32+B33*B34 -> 0.042183 | C35: =C32+C33*C34 -> 0.046583 | D35: =D32+D33*D34 -> 0.087683 | E35: =E32+E33*E34 -> 0.085283 | F35: =F32+F33*F34 -> 0.082483 | G35: =G32+G33*G34 -> 0.082183 | H35: =H32+H33*H34 -> 0.085983 | I35: =I32+I33*I34 -> 0.085983 | ... L35: =L32+L33*L34 -> 0.085983
A36: Target equity weight/actual equity weight | B36: ='3-Statement Model'!B65/('3-Statement Model'!B65+B12) -> 0.60598865 | C36: ='3-Statement Model'!C65/('3-Statement Model'!C65+C12) -> 0.6754563 | D36: ='3-Statement Model'!D65/('3-Statement Model'!D65+D12) -> 0.70199764 | E36: ='3-Statement Model'!E65/('3-Statement Model'!E65+E12) -> 0.82692633 | F36: ='3-Statement Model'!F65/('3-Statement Model'!F65+F12) -> 0.86728748 | G36: ='3-Statement Model'!G65/('3-Statement Model'!G65+G12) -> 0.91987096 | H36: =Assumptions!B16 -> 0.95 | I36: =Assumptions!B16 -> 0.95 | J36: =Assumptions!B16 -> 0.95 | K36: =Assumptions!B16 -> 0.95 | L36: =Assumptions!B16 -> 0.95
A37: Target debt weight/actual debt weight | B37: =1-B36 -> 0.39401135 | C37: =1-C36 -> 0.3245437 | D37: =1-D36 -> 0.29800236 | E37: =1-E36 -> 0.17307367 | F37: =1-F36 -> 0.13271252 | G37: =1-G36 -> 0.080129041 | H37: =Assumptions!B17 -> 0.05 | I37: =Assumptions!B17 -> 0.05 | J37: =Assumptions!B17 -> 0.05 | K37: =Assumptions!B17 -> 0.05 | L37: =Assumptions!B17 -> 0.05
A38: WACC | B38: =B35*B36+B31*B37 -> 0.032191038 | C38: =C35*C36+C31*C37 -> 0.036203272 | D38: =D35*D36+D31*D37 -> 0.079988477 | E38: =E35*E36+E31*E37 -> 0.082561059 | F38: =F35*F36+F31*F37 -> 0.080504583 | G38: =G35*G36+G31*G37 -> 0.080380149 | H38: =H35*H36+H31*H37 -> 0.08451885 | I38: =I35*I36+I31*I37 -> 0.08451885 | ... L38: =L35*L36+L31*L37 -> 0.08451885

Sheet DCF Valuation
A1: DCF Valuation | I1: Sensitivity Analysis — Implied Value / Share (PLN)
A2: Nominal unlevered DCF with two CapEx scenarios. Scenario 1 continues increasing CapEx; Scenario 2 assumes terminal-year CapEx equals D&A. | I2: Rows = terminal growth; columns = WACC. Formulas reference the existing DCF and do not change model assumptions.
A3: Metric | B3: 2026E | C3: 2027E | D3: 2028E | E3: 2029E | F3: 2030E | G3: Terminal
A4: Key Valuation Assumptions | I4: Scenario 1: CapEx Continues Increasing
A5: WACC | B5: ='Debt & WACC'!H38 -> 0.08451885 | I5: g \ WACC | J5: =$B$5-1% -> 0.07451885 | K5: =$B$5-0.5% -> 0.07951885 | L5: =$B$5 -> 0.08451885 | M5: =$B$5+0.5% -> 0.08951885 | N5: =$B$5+1% -> 0.09451885
A6: Terminal growth rate | B6: =Assumptions!B8 -> 0.03 | I6: =$B$6-1% -> 0.02 | J6: =IF(J$5>$I6,((SUMPRODUCT($B$14:$F$14,1/(1+J$5)^$B$16:$F$16)+($F$14*(1+$I6)/(J$5-$I6))/(1+J$5)^$F$16)-$B$23)/$B$25,NA()) -> 11.08389 | K6: =IF(K$5>$I6,((SUMPRODUCT($B$14:$F$14,1/(1+K$5)^$B$16:$F$16)+($F$14*(1+$I6)/(K$5-$I6))/(1+K$5)^$F$16)-$B$23)/$B$25,NA()) -> 9.9042686 | L6: =IF(L$5>$I6,((SUMPRODUCT($B$14:$F$14,1/(1+L$5)^$B$16:$F$16)+($F$14*(1+$I6)/(L$5-$I6))/(1+L$5)^$F$16)-$B$23)/$B$25,NA()) -> 8.9116199 | M6: =IF(M$5>$I6,((SUMPRODUCT($B$14:$F$14,1/(1+M$5)^$B$16:$F$16)+($F$14*(1+$I6)/(M$5-$I6))/(1+M$5)^$F$16)-$B$23)/$B$25,NA()) -> 8.0655127 | N6: =IF(N$5>$I6,((SUMPRODUCT($B$14:$F$14,1/(1+N$5)^$B$16:$F$16)+($F$14*(1+$I6)/(N$5-$I6))/(1+N$5)^$F$16)-$B$23)/$B$25,NA()) -> 7.3363693
A7: Unlevered Free Cash Flow | I7: =$B$6-0.5% -> 0.025 | J7: =IF(J$5>$I7,((SUMPRODUCT($B$14:$F$14,1/(1+J$5)^$B$16:$F$16)+($F$14*(1+$I7)/(J$5-$I7))/(1+J$5)^$F$16)-$B$23)/$B$25,NA()) -> 12.264073 | K7: =IF(K$5>$I7,((SUMPRODUCT($B$14:$F$14,1/(1+K$5)^$B$16:$F$16)+($F$14*(1+$I7)/(K$5-$I7))/(1+K$5)^$F$16)-$B$23)/$B$25,NA()) -> 10.868099 | L7: =IF(L$5>$I7,((SUMPRODUCT($B$14:$F$14,1/(1+L$5)^$B$16:$F$16)+($F$14*(1+$I7)/(L$5-$I7))/(1+L$5)^$F$16)-$B$23)/$B$25,NA()) -> 9.711147 | M7: =IF(M$5>$I7,((SUMPRODUCT($B$14:$F$14,1/(1+M$5)^$B$16:$F$16)+($F$14*(1+$I7)/(M$5-$I7))/(1+M$5)^$F$16)-$B$23)/$B$25,NA()) -> 8.7375519 | N7: =IF(N$5>$I7,((SUMPRODUCT($B$14:$F$14,1/(1+N$5)^$B$16:$F$16)+($F$14*(1+$I7)/(N$5-$I7))/(1+N$5)^$F$16)-$B$23)/$B$25,NA()) -> 7.9076652
A8: EBIT | B8: ='3-Statement Model'!H18 -> 2032908.3 | C8: ='3-Statement Model'!I18 -> 2560049 | D8: ='3-Statement Model'!J18 -> 3132970.1 | E8: ='3-Statement Model'!K18 -> 3718582.5 | F8: ='3-Statement Model'!L18 -> 4275884.9 | I8: =$B$6 -> 0.03 | J8: =IF(J$5>$I8,((SUMPRODUCT($B$14:$F$14,1/(1+J$5)^$B$16:$F$16)+($F$14*(1+$I8)/(J$5-$I8))/(1+J$5)^$F$16)-$B$23)/$B$25,NA()) -> 13.709354 | K8: =IF(K$5>$I8,((SUMPRODUCT($B$14:$F$14,1/(1+K$5)^$B$16:$F$16)+($F$14*(1+$I8)/(K$5-$I8))/(1+K$5)^$F$16)-$B$23)/$B$25,NA()) -> 12.026569 | L8: =IF(L$5>$I8,((SUMPRODUCT($B$14:$F$14,1/(1+L$5)^$B$16:$F$16)+($F$14*(1+$I8)/(L$5-$I8))/(1+L$5)^$F$16)-$B$23)/$B$25,NA()) -> 10.657326 | M8: =IF(M$5>$I8,((SUMPRODUCT($B$14:$F$14,1/(1+M$5)^$B$16:$F$16)+($F$14*(1+$I8)/(M$5-$I8))/(1+M$5)^$F$16)-$B$23)/$B$25,NA()) -> 9.5225031 | N8: =IF(N$5>$I8,((SUMPRODUCT($B$14:$F$14,1/(1+N$5)^$B$16:$F$16)+($F$14*(1+$I8)/(N$5-$I8))/(1+N$5)^$F$16)-$B$23)/$B$25,NA()) -> 8.5675082
A9: Cash taxes on EBIT | B9: =-B8*Assumptions!B15 -> -386252.59 | C9: =-C8*Assumptions!B15 -> -486409.31 | D9: =-D8*Assumptions!B15 -> -595264.31 | E9: =-E8*Assumptions!B15 -> -706530.68 | F9: =-F8*Assumptions!B15 -> -812418.14 | I9: =$B$6+0.5% -> 0.035 | J9: =IF(J$5>$I9,((SUMPRODUCT($B$14:$F$14,1/(1+J$5)^$B$16:$F$16)+($F$14*(1+$I9)/(J$5-$I9))/(1+J$5)^$F$16)-$B$23)/$B$25,NA()) -> 15.520354 | K9: =IF(K$5>$I9,((SUMPRODUCT($B$14:$F$14,1/(1+K$5)^$B$16:$F$16)+($F$14*(1+$I9)/(K$5-$I9))/(1+K$5)^$F$16)-$B$23)/$B$25,NA()) -> 13.445258 | L9: =IF(L$5>$I9,((SUMPRODUCT($B$14:$F$14,1/(1+L$5)^$B$16:$F$16)+($F$14*(1+$I9)/(L$5-$I9))/(1+L$5)^$F$16)-$B$23)/$B$25,NA()) -> 11.794579 | M9: =IF(M$5>$I9,((SUMPRODUCT($B$14:$F$14,1/(1+M$5)^$B$16:$F$16)+($F$14*(1+$I9)/(M$5-$I9))/(1+M$5)^$F$16)-$B$23)/$B$25,NA()) -> 10.451432 | N9: =IF(N$5>$I9,((SUMPRODUCT($B$14:$F$14,1/(1+N$5)^$B$16:$F$16)+($F$14*(1+$I9)/(N$5-$I9))/(1+N$5)^$F$16)-$B$23)/$B$25,NA()) -> 9.3382141
A10: NOPAT | B10: =B8+B9 -> 1646655.8 | C10: =C8+C9 -> 2073639.7 | D10: =D8+D9 -> 2537705.8 | E10: =E8+E9 -> 3012051.8 | F10: =F8+F9 -> 3463466.8 | I10: =$B$6+1% -> 0.04 | J10: =IF(J$5>$I10,((SUMPRODUCT($B$14:$F$14,1/(1+J$5)^$B$16:$F$16)+($F$14*(1+$I10)/(J$5-$I10))/(1+J$5)^$F$16)-$B$23)/$B$25,NA()) -> 17.855994 | K10: =IF(K$5>$I10,((SUMPRODUCT($B$14:$F$14,1/(1+K$5)^$B$16:$F$16)+($F$14*(1+$I10)/(K$5-$I10))/(1+K$5)^$F$16)-$B$23)/$B$25,NA()) -> 15.222939 | L10: =IF(L$5>$I10,((SUMPRODUCT($B$14:$F$14,1/(1+L$5)^$B$16:$F$16)+($F$14*(1+$I10)/(L$5-$I10))/(1+L$5)^$F$16)-$B$23)/$B$25,NA()) -> 13.187286 | M10: =IF(M$5>$I10,((SUMPRODUCT($B$14:$F$14,1/(1+M$5)^$B$16:$F$16)+($F$14*(1+$I10)/(M$5-$I10))/(1+M$5)^$F$16)-$B$23)/$B$25,NA()) -> 11.567952 | N10: =IF(N$5>$I10,((SUMPRODUCT($B$14:$F$14,1/(1+N$5)^$B$16:$F$16)+($F$14*(1+$I10)/(N$5-$I10))/(1+N$5)^$F$16)-$B$23)/$B$25,NA()) -> 10.250285
A11: D&A addback | B11: ='3-Statement Model'!H32 -> 579936.92 | C11: ='3-Statement Model'!I32 -> 657416.49 | D11: ='3-Statement Model'!J32 -> 734860.15 | E11: ='3-Statement Model'!K32 -> 809889.37 | F11: ='3-Statement Model'!L32 -> 882520.25
A12: Capital expenditures | B12: ='3-Statement Model'!H35 -> -2435735.1 | C12: ='3-Statement Model'!I35 -> -2673493.7 | D12: ='3-Statement Model'!J35 -> -2890449.9 | E12: ='3-Statement Model'!K35 -> -3077579.6 | F12: ='3-Statement Model'!L35 -> -3235907.6 | I12: Scenario 2: Terminal CapEx = D&A
A13: Less: change in operating NWC | B13: =-'3-Statement Model'!H33 -> -860848.26 | C13: =-'3-Statement Model'!I33 -> -298280.4 | D13: =-'3-Statement Model'!J33 -> -296428.15 | E13: =-'3-Statement Model'!K33 -> -286852.91 | F13: =-'3-Statement Model'!L33 -> -277249.95 | I13: g \ WACC | J13: =$B$5-1% -> 0.07451885 | K13: =$B$5-0.5% -> 0.07951885 | L13: =$B$5 -> 0.08451885 | M13: =$B$5+0.5% -> 0.08951885 | N13: =$B$5+1% -> 0.09451885
A14: Unlevered free cash flow | B14: =SUM(B10:B13) -> -1069990.6 | C14: =SUM(C10:C13) -> -240717.94 | D14: =SUM(D10:D13) -> 85687.823 | E14: =SUM(E10:E13) -> 457508.69 | F14: =SUM(F10:F13) -> 832829.51 | I14: =$B$6-1% -> 0.02 | J14: =IF(J$13>$I14,((SUMPRODUCT($B$14:$F$14,1/(1+J$13)^$B$16:$F$16)+($B$34*(1+$I14)/(J$13-$I14))/(1+J$13)^$F$16)-$B$23)/$B$25,NA()) -> 42.436479 | K14: =IF(K$13>$I14,((SUMPRODUCT($B$14:$F$14,1/(1+K$13)^$B$16:$F$16)+($B$34*(1+$I14)/(K$13-$I14))/(1+K$13)^$F$16)-$B$23)/$B$25,NA()) -> 37.96407 | L14: =IF(L$13>$I14,((SUMPRODUCT($B$14:$F$14,1/(1+L$13)^$B$16:$F$16)+($B$34*(1+$I14)/(L$13-$I14))/(1+L$13)^$F$16)-$B$23)/$B$25,NA()) -> 34.205656 | M14: =IF(M$13>$I14,((SUMPRODUCT($B$14:$F$14,1/(1+M$13)^$B$16:$F$16)+($B$34*(1+$I14)/(M$13-$I14))/(1+M$13)^$F$16)-$B$23)/$B$25,NA()) -> 31.006598 | N14: =IF(N$13>$I14,((SUMPRODUCT($B$14:$F$14,1/(1+N$13)^$B$16:$F$16)+($B$34*(1+$I14)/(N$13-$I14))/(1+N$13)^$F$16)-$B$23)/$B$25,NA()) -> 28.253779
A15: Discounting | I15: =$B$6-0.5% -> 0.025 | J15: =IF(J$13>$I15,((SUMPRODUCT($B$14:$F$14,1/(1+J$13)^$B$16:$F$16)+($B$34*(1+$I15)/(J$13-$I15))/(1+J$13)^$F$16)-$B$23)/$B$25,NA()) -> 46.951592 | K15: =IF(K$13>$I15,((SUMPRODUCT($B$14:$F$14,1/(1+K$13)^$B$16:$F$16)+($B$34*(1+$I15)/(K$13-$I15))/(1+K$13)^$F$16)-$B$23)/$B$25,NA()) -> 41.651467 | L15: =IF(L$13>$I15,((SUMPRODUCT($B$14:$F$14,1/(1+L$13)^$B$16:$F$16)+($B$34*(1+$I15)/(L$13-$I15))/(1+L$13)^$F$16)-$B$23)/$B$25,NA()) -> 37.264466 | M15: =IF(M$13>$I15,((SUMPRODUCT($B$14:$F$14,1/(1+M$13)^$B$16:$F$16)+($B$34*(1+$I15)/(M$13-$I15))/(1+M$13)^$F$16)-$B$23)/$B$25,NA()) -> 33.577668 | N15: =IF(N$13>$I15,((SUMPRODUCT($B$14:$F$14,1/(1+N$13)^$B$16:$F$16)+($B$34*(1+$I15)/(N$13-$I15))/(1+N$13)^$F$16)-$B$23)/$B$25,NA()) -> 30.439428
A16: Discount period | B16: =1 -> 1 | C16: =2 -> 2 | D16: =3 -> 3 | E16: =4 -> 4 | F16: =5 -> 5 | I16: =$B$6 -> 0.03 | J16: =IF(J$13>$I16,((SUMPRODUCT($B$14:$F$14,1/(1+J$13)^$B$16:$F$16)+($B$34*(1+$I16)/(J$13-$I16))/(1+J$13)^$F$16)-$B$23)/$B$25,NA()) -> 52.480908 | K16: =IF(K$13>$I16,((SUMPRODUCT($B$14:$F$14,1/(1+K$13)^$B$16:$F$16)+($B$34*(1+$I16)/(K$13-$I16))/(1+K$13)^$F$16)-$B$23)/$B$25,NA()) -> 46.083509 | L16: =IF(L$13>$I16,((SUMPRODUCT($B$14:$F$14,1/(1+L$13)^$B$16:$F$16)+($B$34*(1+$I16)/(L$13-$I16))/(1+L$13)^$F$16)-$B$23)/$B$25,NA()) -> 40.884331 | M16: =IF(M$13>$I16,((SUMPRODUCT($B$14:$F$14,1/(1+M$13)^$B$16:$F$16)+($B$34*(1+$I16)/(M$13-$I16))/(1+M$13)^$F$16)-$B$23)/$B$25,NA()) -> 36.580713 | N16: =IF(N$13>$I16,((SUMPRODUCT($B$14:$F$14,1/(1+N$13)^$B$16:$F$16)+($B$34*(1+$I16)/(N$13-$I16))/(1+N$13)^$F$16)-$B$23)/$B$25,NA()) -> 32.963838
A17: Discount factor | B17: =1/(1+$B$5)^B16 -> 0.92206788 | C17: =1/(1+$B$5)^C16 -> 0.85020918 | D17: =1/(1+$B$5)^D16 -> 0.78395058 | E17: =1/(1+$B$5)^E16 -> 0.72285565 | F17: =1/(1+$B$5)^F16 -> 0.66652198 | I17: =$B$6+0.5% -> 0.035 | J17: =IF(J$13>$I17,((SUMPRODUCT($B$14:$F$14,1/(1+J$13)^$B$16:$F$16)+($B$34*(1+$I17)/(J$13-$I17))/(1+J$13)^$F$16)-$B$23)/$B$25,NA()) -> 59.409382 | K17: =IF(K$13>$I17,((SUMPRODUCT($B$14:$F$14,1/(1+K$13)^$B$16:$F$16)+($B$34*(1+$I17)/(K$13-$I17))/(1+K$13)^$F$16)-$B$23)/$B$25,NA()) -> 51.511094 | L17: =IF(L$13>$I17,((SUMPRODUCT($B$14:$F$14,1/(1+L$13)^$B$16:$F$16)+($B$34*(1+$I17)/(L$13-$I17))/(1+L$13)^$F$16)-$B$23)/$B$25,NA()) -> 45.235204 | M17: =IF(M$13>$I17,((SUMPRODUCT($B$14:$F$14,1/(1+M$13)^$B$16:$F$16)+($B$34*(1+$I17)/(M$13-$I17))/(1+M$13)^$F$16)-$B$23)/$B$25,NA()) -> 40.134585 | N17: =IF(N$13>$I17,((SUMPRODUCT($B$14:$F$14,1/(1+N$13)^$B$16:$F$16)+($B$34*(1+$I17)/(N$13-$I17))/(1+N$13)^$F$16)-$B$23)/$B$25,NA()) -> 35.912384
A18: PV of unlevered FCF | B18: =B14*B17 -> -986604 | C18: =C14*C17 -> -204660.6 | D18: =D14*D17 -> 67175.018 | E18: =E14*E17 -> 330712.74 | F18: =F14*F17 -> 555099.17 | I18: =$B$6+1% -> 0.04 | J18: =IF(J$13>$I18,((SUMPRODUCT($B$14:$F$14,1/(1+J$13)^$B$16:$F$16)+($B$34*(1+$I18)/(J$13-$I18))/(1+J$13)^$F$16)-$B$23)/$B$25,NA()) -> 68.345014 | K18: =IF(K$13>$I18,((SUMPRODUCT($B$14:$F$14,1/(1+K$13)^$B$16:$F$16)+($B$34*(1+$I18)/(K$13-$I18))/(1+K$13)^$F$16)-$B$23)/$B$25,NA()) -> 58.312096 | L18: =IF(L$13>$I18,((SUMPRODUCT($B$14:$F$14,1/(1+L$13)^$B$16:$F$16)+($B$34*(1+$I18)/(L$13-$I18))/(1+L$13)^$F$16)-$B$23)/$B$25,NA()) -> 50.563387 | M18: =IF(M$13>$I18,((SUMPRODUCT($B$14:$F$14,1/(1+M$13)^$B$16:$F$16)+($B$34*(1+$I18)/(M$13-$I18))/(1+M$13)^$F$16)-$B$23)/$B$25,NA()) -> 44.406138 | N18: =IF(N$13>$I18,((SUMPRODUCT($B$14:$F$14,1/(1+N$13)^$B$16:$F$16)+($B$34*(1+$I18)/(N$13-$I18))/(1+N$13)^$F$16)-$B$23)/$B$25,NA()) -> 39.40176
A19: Terminal value | G19: =F14*(1+$B$6)/($B$5-$B$6) -> 15734272
A20: PV of terminal value | G20: =G19*F17 -> 10487238
A21: Valuation Summary — Scenario 1: CapEx Continues Increasing
A22: Enterprise value | B22: =SUM(B18:F18)+G20 -> 10248960
A23: Less: net debt / (net cash) | B23: ='3-Statement Model'!G89 -> -199482
A24: Equity value | B24: =B22-B23 -> 10448442
A25: Shares outstanding ('000) | B25: =Assumptions!B10 -> 980400
A26: Implied value / share (PLN) | B26: =B24/B25 -> 10.657326
A27: Current share price (PLN) | B27: =Assumptions!B9 -> 32.84
A28: Premium / (discount) | B28: =B26/B27-1 -> -0.67547729
A29: Valuation Summary — Scenario 2: Terminal CapEx = D&A
A30: Terminal-year NOPAT | B30: =F10 -> 3463466.8
A31: Terminal-year D&A | B31: =F11 -> 882520.25
A32: Terminal-year CapEx assumption | B32: =-B31 -> -882520.25
A33: Terminal-year change in NWC | B33: =F13 -> -277249.95
A34: Terminal-year UFCF | B34: =SUM(B30:B33) -> 3186216.8
A35: Terminal value | B35: =B34*(1+$B$6)/($B$5-$B$6) -> 60195755
A36: PV of terminal value | B36: =B35*F17 -> 40121794
A37: Enterprise value | B37: =SUM(B18:F18)+B36 -> 39883516
A38: Implied value / share (PLN) | B38: =(B37-B23)/B25 -> 40.884331
A39: Premium / (discount) | B39: =B38/B27-1 -> 0.24495527

Sheet Checks
A1: Model Checks
A2: All checks should equal zero. This sheet also confirms that DCF and debt schedules tie to source formulas.
A3: Metric | B3: 2020 | C3: 2021 | D3: 2022 | E3: 2023 | F3: 2024 | G3: 2025 | H3: 2026 | I3: 2027 | J3: 2028 | K3: 2029 | L3: 2030
A4: Balance sheet check | B4: ='3-Statement Model'!B86 -> 0 | C4: ='3-Statement Model'!C86 -> 0 | D4: ='3-Statement Model'!D86 -> 0 | E4: ='3-Statement Model'!E86 -> 0 | F4: ='3-Statement Model'!F86 -> 0 | G4: ='3-Statement Model'!G86 -> 0 | H4: ='3-Statement Model'!H86 -> 0 | I4: ='3-Statement Model'!I86 -> 0 | ... L4: ='3-Statement Model'!L86 -> 0
A5: Cash flow check | B5: ='3-Statement Model'!B87 -> 0 | C5: ='3-Statement Model'!C87 -> 0 | D5: ='3-Statement Model'!D87 -> 0 | E5: ='3-Statement Model'!E87 -> 0 | F5: ='3-Statement Model'!F87 -> 0 | G5: ='3-Statement Model'!G87 -> 0 | H5: ='3-Statement Model'!H87 -> 0 | I5: ='3-Statement Model'!I87 -> 0 | ... L5: ='3-Statement Model'!L87 -> 0
A6: Debt schedule tie to 3-stmt | B6: ='Debt & WACC'!B12-'3-Statement Model'!B88 -> 0 | C6: ='Debt & WACC'!C12-'3-Statement Model'!C88 -> 0 | D6: ='Debt & WACC'!D12-'3-Statement Model'!D88 -> 0 | E6: ='Debt & WACC'!E12-'3-Statement Model'!E88 -> 0 | F6: ='Debt & WACC'!F12-'3-Statement Model'!F88 -> 0 | G6: ='Debt & WACC'!G12-'3-Statement Model'!G88 -> 0 | H6: ='Debt & WACC'!H12-'3-Statement Model'!H88 -> 0 | I6: ='Debt & WACC'!I12-'3-Statement Model'!I88 -> 0 | ... L6: ='Debt & WACC'!L12-'3-Statement Model'!L88 -> 0
A7: Cash tie to debt/WACC | B7: ='Debt & WACC'!B13-'3-Statement Model'!B56 -> 0 | C7: ='Debt & WACC'!C13-'3-Statement Model'!C56 -> 0 | D7: ='Debt & WACC'!D13-'3-Statement Model'!D56 -> 0 | E7: ='Debt & WACC'!E13-'3-Statement Model'!E56 -> 0 | F7: ='Debt & WACC'!F13-'3-Statement Model'!F56 -> 0 | G7: ='Debt & WACC'!G13-'3-Statement Model'!G56 -> 0 | H7: ='Debt & WACC'!H13-'3-Statement Model'!H56 -> 0 | I7: ='Debt & WACC'!I13-'3-Statement Model'!I56 -> 0 | ... L7: ='Debt & WACC'!L13-'3-Statement Model'!L56 -> 0
A8: DCF WACC source check | H8: ='DCF Valuation'!B5-'Debt & WACC'!H38 -> 0
A9: CapEx growth check | H9: =IF(ABS('3-Statement Model'!H35)>ABS('3-Statement Model'!G35),0,1) -> 0 | I9: =IF(ABS('3-Statement Model'!I35)>ABS('3-Statement Model'!H35),0,1) -> 0 | J9: =IF(ABS('3-Statement Model'!J35)>ABS('3-Statement Model'!I35),0,1) -> 0 | K9: =IF(ABS('3-Statement Model'!K35)>ABS('3-Statement Model'!J35),0,1) -> 0 | L9: =IF(ABS('3-Statement Model'!L35)>ABS('3-Statement Model'!K35),0,1) -> 0
A10: Scenario 2 terminal CapEx = D&A check | H10: ='DCF Valuation'!B32+'DCF Valuation'!B31 -> 0
